Workbook

Sheet Dashboard
A2: Accounting Project Dashboard
A3: Created by: Arjunkumar Kori
A4: Date: December 26, 2025
A6: Main Sections | B6: Click to Jump
A7: 1. Weekly Payroll Processing | B7: Payroll.xlsx
A8: 2. Accounts Receivable & Aging | B8: AR and Journal Entry1.xlsx
A9: 3. Bank Reconciliation | B9: Bank Reconciliation.xlsx
A10: 4. Credit Card Reconciliation | B10: Credit Card Reconciliation and Journal Entries ^0 Month-End Adjustments.xlsx
A11: 5. Journal Entries & Month-End Adjustments | B11: Credit Card Reconciliation and Journal Entries ^0 Month-End Adjustments.xlsx
A12: 6. Tax Filing (HST / WSIB / EHT) | B12: Trail balance and Tax Filing (HST^LLJ WSIB^LLJ EHT).xlsx
A13: 7. Vehicle Sales (New & Used) | B13: Vehicle Sales (New ^0 Used).xlsx
A14: Bonus: Chart of Accounts | B14: Bonus – Chart of Accounts.xlsx
A16: Quick Summary / Key Figures
A17: Description | B17: Value | C17: Notes
A18: Total Sales Revenue (New + Used + Service + Parts) | B18: 221800 | C18: From trial balance (all revenue accounts)
A19: Total COGS | B19: 1183000 | C19: Sum of COGS accounts
A20: Gross Profit (approx.) | B20: 1035000 | C20: Revenue - COGS
A21: Total HST Payable (Q4 before payment) | B21: 109103.8 | C21: Opening + Net Q4
A22: Total Employees | B22: 30 | C22: From payroll section
A23: Total Payroll Expense | B23: 293400 | C23: Salaries + Overtime
A24: Net HST Remitted (Q4) | B24: 109103.8 | C24: Full amount paid to CRA
A26: Instructions:
A27: • Click any section name above to jump directly to that sheet
A28: • All major sections are linked for easy navigation
A29: • Formulas are dynamic where possible – totals update automatically
A30: • Project covers full accounting cycle: Payroll → Sales → Reconciliations → Taxes → Reporting

Sheet Payroll_Master
A1: Emp_ID | B1: Last_Name | C1: First_Name | D1: Department | E1: Pay_Type | F1: Hourly_Rate | G1: Annual_Salary | H1: Hire_Date
A2: E001 | B2: Smith | C2: John | D2: Sales | E2: Hourly | F2: 25 | H2: 44635
A3: E002 | B3: Johnson | C3: Sarah | D3: Service | E3: Hourly | F3: 22 | H3: 44367
A4: E003 | B4: Williams | C4: Mike | D4: Parts | E4: Hourly | F4: 28 | H4: 43840
A5: E004 | B5: Davis | C5: Emily | D5: Sales | E5: Hourly | F5: 30 | H5: 44971
A6: E005 | B6: Brown | C6: Robert | D6: Management | E6: Salary | G6: 125000 | H6: 43586
A7: E006 | B7: Garcia | C7: Maria | D7: Sales | E7: Hourly | F7: 26.5 | H7: 44785
A8: E007 | B8: Martinez | C8: Carlos | D8: Service | E8: Hourly | F8: 24 | H8: 44503
A9: E008 | B9: Rodriguez | C9: Ana | D9: Finance | E9: Salary | G9: 85000 | H9: 44027
A10: E009 | B10: Wilson | C10: James | D10: Parts | E10: Hourly | F10: 23.5 | H10: 44946
A11: E010 | B11: Lopez | C11: Sofia | D11: Sales | E11: Hourly | F11: 27 | H11: 44669
A12: E011 | B12: Lee | C12: Kevin | D12: Service | E12: Hourly | F12: 21.5 | H12: 45102
A13: E012 | B13: Walker | C13: Lisa | D13: HR | E13: Salary | G13: 75000 | H13: 44449
A14: E013 | B14: Hall | C14: David | D14: Sales | E14: Hourly | F14: 29 | H14: 44170
A15: E014 | B15: Allen | C15: Jessica | D15: Parts | E15: Hourly | F15: 22.5 | H15: 44864
A16: E015 | B16: Young | C16: Michael | D16: Service | E16: Hourly | F16: 25.5 | H16: 44277
A17: E016 | B17: King | C17: Amanda | D17: Sales | E17: Hourly | F17: 28.5 | H17: 45033
A18: E017 | B18: Wright | C18: Daniel | D18: Finance | E18: Hourly | F18: 32 | H18: 44051
A19: E018 | B19: Scott | C19: Nicole | D19: Service | E19: Hourly | F19: 23 | H19: 44756
A20: E019 | B20: Green | C20: Christopher | D20: Parts | E20: Hourly | F20: 24.5 | H20: 44531
A21: E020 | B21: Baker | C21: Michelle | D21: Sales | E21: Hourly | F21: 26 | H21: 45055
A22: E021 | B22: Nelson | C22: Ryan | D22: Management | E22: Salary | G22: 95000 | H22: 43789
A23: E022 | B23: Carter | C23: Ashley | D23: Service | E23: Hourly | F23: 22.5 | H23: 44620
A24: E023 | B24: Mitchell | C24: Brandon | D24: Parts | E24: Hourly | F24: 27.5 | H24: 44332
A25: E024 | B25: Perez | C25: Samantha | D25: Sales | E25: Hourly | F25: 25.5 | H25: 44992
A26: E025 | B26: Roberts | C26: Justin | D26: Service | E26: Hourly | F26: 24 | H26: 44099
A27: E026 | B27: Turner | C27: Rachel | D27: Finance | E27: Salary | G27: 80000 | H27: 44388
A28: E027 | B28: Phillips | C28: Matthew | D28: Sales | E28: Hourly | F28: 29.5 | H28: 44884
A29: E028 | B29: Campbell | C29: Lauren | D29: Parts | E29: Hourly | F29: 23.5 | H29: 45137
A30: E029 | B30: Parker | C30: Andrew | D30: Service | E30: Hourly | F30: 26.5 | H30: 43934
A31: E030 | B31: Evans | C31: Megan | D31: Sales | E31: Hourly | F31: 28 | H31: 44809

Sheet Payroll_Weekly
A1: Emp_ID | B1: Week_Ending | C1: Regular_Hours | D1: Overtime_Hours | E1: Sick_Hours | F1: Vacation_Hours | G1: Total_Hours
A2: E001 | B2: 45639 | C2: 40 | D2: 5 | E2: 0 | F2: 0 | G2: =SUM(tbl_Timesheet[[#This Row],[Regular_Hours]:[Vacation_Hours]]) -> 45
A3: E002 | B3: 45639 | C3: 40 | D3: 0 | E3: 0 | F3: 0 | G3: =SUM(tbl_Timesheet[[#This Row],[Regular_Hours]:[Vacation_Hours]]) -> 40
A4: E003 | B4: 45639 | C4: 37.5 | D4: 3 | E4: 0 | F4: 0 | G4: =SUM(tbl_Timesheet[[#This Row],[Regular_Hours]:[Vacation_Hours]]) -> 40.5
A5: E004 | B5: 45639 | C5: 40 | D5: 2 | E5: 0 | F5: 0 | G5: =SUM(tbl_Timesheet[[#This Row],[Regular_Hours]:[Vacation_Hours]]) -> 42
A6: E005 | B6: 45639 | C6: 40 | D6: 0 | E6: 0 | F6: 0 | G6: =SUM(tbl_Timesheet[[#This Row],[Regular_Hours]:[Vacation_Hours]]) -> 40
A7: E006 | B7: 45639 | C7: 40 | D7: 4 | E7: 0 | F7: 0 | G7: =SUM(tbl_Timesheet[[#This Row],[Regular_Hours]:[Vacation_Hours]]) -> 44
A8: E007 | B8: 45639 | C8: 40 | D8: 1.5 | E8: 0 | F8: 0 | G8: =SUM(tbl_Timesheet[[#This Row],[Regular_Hours]:[Vacation_Hours]]) -> 41.5
A9: E008 | B9: 45639 | C9: 40 | D9: 0 | E9: 0 | F9: 0 | G9: =SUM(tbl_Timesheet[[#This Row],[Regular_Hours]:[Vacation_Hours]]) -> 40
A10: E009 | B10: 45639 | C10: 38 | D10: 0 | E10: 0 | F10: 0 | G10: =SUM(tbl_Timesheet[[#This Row],[Regular_Hours]:[Vacation_Hours]]) -> 38
A11: E010 | B11: 45639 | C11: 40 | D11: 6 | E11: 0 | F11: 0 | G11: =SUM(tbl_Timesheet[[#This Row],[Regular_Hours]:[Vacation_Hours]]) -> 46
A12: E011 | B12: 45639 | C12: 40 | D12: 0 | E12: 0 | F12: 0 | G12: =SUM(tbl_Timesheet[[#This Row],[Regular_Hours]:[Vacation_Hours]]) -> 40
A13: E012 | B13: 45639 | C13: 40 | D13: 0 | E13: 0 | F13: 0 | G13: =SUM(tbl_Timesheet[[#This Row],[Regular_Hours]:[Vacation_Hours]]) -> 40
... A31: E030 | B31: 45639 | C31: 40 | D31: 4 | E31: 0 | F31: 0 | G31: =SUM(tbl_Timesheet[[#This Row],[Regular_Hours]:[Vacation_Hours]]) -> 44

Sheet Payroll_Calc
A1: Emp_ID | B1: Employee_Name | C1: Regular_Pay | D1: Overtime_Pay | E1: Gross_Pay | F1: CPP | G1: EI | H1: Fed_Tax | I1: Prov_Tax | J1: Total_Deductions | K1: Net_Pay
A2: =tbl_Timesheet[[#This Row],[Emp_ID]] -> E001 | B2: =VLOOKUP(A2,tbl_Employees[],3,FALSE)&" "&VLOOKUP(A2,tbl_Employees[],2,FALSE) -> John Smith | C2: =IF(VLOOKUP(A2,tbl_Employees[],5,FALSE)="Hourly", VLOOKUP(A2,tbl_Employees[],6,FALSE)*VLOOKUP(A2,tbl_Timesheet[],3,FALSE), VLOOKUP(A2,tbl_Employees[],7,FALSE)/26) -> 1000 | D2: =IF(VLOOKUP(A2,tbl_Employees[],5,FALSE)="Hourly", VLOOKUP(A2,tbl_Employees[],6,FALSE)*1.5*VLOOKUP(A2,tbl_Timesheet[],4,FALSE), 0) -> 187.5 | E2: =C2+D2 -> 1187.5 | F2: =MAX(0,MIN((E2-67.31)*0.0595,67.58)) -> 66.651305 | G2: =MIN(E2*0.0166,20.19) -> 19.7125 | H2: =IF(E2>735,E2*0.15,E2*0.05) -> 178.125 | I2: =IF(E2>735,E2*0.0505,E2*0.02) -> 59.96875 | J2: =SUM(F2:I2) -> 324.45755 | K2: =E2-J2 -> 863.04245
A3: =tbl_Timesheet[[#This Row],[Emp_ID]] -> E002 | B3: =VLOOKUP(A3,tbl_Employees[],3,FALSE)&" "&VLOOKUP(A3,tbl_Employees[],2,FALSE) -> Sarah Johnson | C3: =IF(VLOOKUP(A3,tbl_Employees[],5,FALSE)="Hourly", VLOOKUP(A3,tbl_Employees[],6,FALSE)*VLOOKUP(A3,tbl_Timesheet[],3,FALSE), VLOOKUP(A3,tbl_Employees[],7,FALSE)/26) -> 880 | D3: =IF(VLOOKUP(A3,tbl_Employees[],5,FALSE)="Hourly", VLOOKUP(A3,tbl_Employees[],6,FALSE)*1.5*VLOOKUP(A3,tbl_Timesheet[],4,FALSE), 0) -> 0 | E3: =C3+D3 -> 880 | F3: =MAX(0,MIN((E3-67.31)*0.0595,67.58)) -> 48.355055 | G3: =MIN(E3*0.0166,20.19) -> 14.608 | H3: =IF(E3>735,E3*0.15,E3*0.05) -> 132 | I3: =IF(E3>735,E3*0.0505,E3*0.02) -> 44.44 | J3: =SUM(F3:I3) -> 239.40305 | K3: =E3-J3 -> 640.59695
A4: =tbl_Timesheet[[#This Row],[Emp_ID]] -> E003 | B4: =VLOOKUP(A4,tbl_Employees[],3,FALSE)&" "&VLOOKUP(A4,tbl_Employees[],2,FALSE) -> Mike Williams | C4: =IF(VLOOKUP(A4,tbl_Employees[],5,FALSE)="Hourly", VLOOKUP(A4,tbl_Employees[],6,FALSE)*VLOOKUP(A4,tbl_Timesheet[],3,FALSE), VLOOKUP(A4,tbl_Employees[],7,FALSE)/26) -> 1050 | D4: =IF(VLOOKUP(A4,tbl_Employees[],5,FALSE)="Hourly", VLOOKUP(A4,tbl_Employees[],6,FALSE)*1.5*VLOOKUP(A4,tbl_Timesheet[],4,FALSE), 0) -> 126 | E4: =C4+D4 -> 1176 | F4: =MAX(0,MIN((E4-67.31)*0.0595,67.58)) -> 65.967055 | G4: =MIN(E4*0.0166,20.19) -> 19.5216 | H4: =IF(E4>735,E4*0.15,E4*0.05) -> 176.4 | I4: =IF(E4>735,E4*0.0505,E4*0.02) -> 59.388 | J4: =SUM(F4:I4) -> 321.27666 | K4: =E4-J4 -> 854.72334
A5: =tbl_Timesheet[[#This Row],[Emp_ID]] -> E004 | B5: =VLOOKUP(A5,tbl_Employees[],3,FALSE)&" "&VLOOKUP(A5,tbl_Employees[],2,FALSE) -> Emily Davis | C5: =IF(VLOOKUP(A5,tbl_Employees[],5,FALSE)="Hourly", VLOOKUP(A5,tbl_Employees[],6,FALSE)*VLOOKUP(A5,tbl_Timesheet[],3,FALSE), VLOOKUP(A5,tbl_Employees[],7,FALSE)/26) -> 1200 | D5: =IF(VLOOKUP(A5,tbl_Employees[],5,FALSE)="Hourly", VLOOKUP(A5,tbl_Employees[],6,FALSE)*1.5*VLOOKUP(A5,tbl_Timesheet[],4,FALSE), 0) -> 90 | E5: =C5+D5 -> 1290 | F5: =MAX(0,MIN((E5-67.31)*0.0595,67.58)) -> 67.58 | G5: =MIN(E5*0.0166,20.19) -> 20.19 | H5: =IF(E5>735,E5*0.15,E5*0.05) -> 193.5 | I5: =IF(E5>735,E5*0.0505,E5*0.02) -> 65.145 | J5: =SUM(F5:I5) -> 346.415 | K5: =E5-J5 -> 943.585
A6: =tbl_Timesheet[[#This Row],[Emp_ID]] -> E005 | B6: =VLOOKUP(A6,tbl_Employees[],3,FALSE)&" "&VLOOKUP(A6,tbl_Employees[],2,FALSE) -> Robert Brown | C6: =IF(VLOOKUP(A6,tbl_Employees[],5,FALSE)="Hourly", VLOOKUP(A6,tbl_Employees[],6,FALSE)*VLOOKUP(A6,tbl_Timesheet[],3,FALSE), VLOOKUP(A6,tbl_Employees[],7,FALSE)/26) -> 4807.6923 | D6: =IF(VLOOKUP(A6,tbl_Employees[],5,FALSE)="Hourly", VLOOKUP(A6,tbl_Employees[],6,FALSE)*1.5*VLOOKUP(A6,tbl_Timesheet[],4,FALSE), 0) -> 0 | E6: =C6+D6 -> 4807.6923 | F6: =MAX(0,MIN((E6-67.31)*0.0595,67.58)) -> 67.58 | G6: =MIN(E6*0.0166,20.19) -> 20.19 | H6: =IF(E6>735,E6*0.15,E6*0.05) -> 721.15385 | I6: =IF(E6>735,E6*0.0505,E6*0.02) -> 242.78846 | J6: =SUM(F6:I6) -> 1051.7123 | K6: =E6-J6 -> 3755.98
A7: =tbl_Timesheet[[#This Row],[Emp_ID]] -> E006 | B7: =VLOOKUP(A7,tbl_Employees[],3,FALSE)&" "&VLOOKUP(A7,tbl_Employees[],2,FALSE) -> Maria Garcia | C7: =IF(VLOOKUP(A7,tbl_Employees[],5,FALSE)="Hourly", VLOOKUP(A7,tbl_Employees[],6,FALSE)*VLOOKUP(A7,tbl_Timesheet[],3,FALSE), VLOOKUP(A7,tbl_Employees[],7,FALSE)/26) -> 1060 | D7: =IF(VLOOKUP(A7,tbl_Employees[],5,FALSE)="Hourly", VLOOKUP(A7,tbl_Employees[],6,FALSE)*1.5*VLOOKUP(A7,tbl_Timesheet[],4,FALSE), 0) -> 159 | E7: =C7+D7 -> 1219 | F7: =MAX(0,MIN((E7-67.31)*0.0595,67.58)) -> 67.58 | G7: =MIN(E7*0.0166,20.19) -> 20.19 | H7: =IF(E7>735,E7*0.15,E7*0.05) -> 182.85 | I7: =IF(E7>735,E7*0.0505,E7*0.02) -> 61.5595 | J7: =SUM(F7:I7) -> 332.1795 | K7: =E7-J7 -> 886.8205
A8: =tbl_Timesheet[[#This Row],[Emp_ID]] -> E007 | B8: =VLOOKUP(A8,tbl_Employees[],3,FALSE)&" "&VLOOKUP(A8,tbl_Employees[],2,FALSE) -> Carlos Martinez | C8: =IF(VLOOKUP(A8,tbl_Employees[],5,FALSE)="Hourly", VLOOKUP(A8,tbl_Employees[],6,FALSE)*VLOOKUP(A8,tbl_Timesheet[],3,FALSE), VLOOKUP(A8,tbl_Employees[],7,FALSE)/26) -> 960 | D8: =IF(VLOOKUP(A8,tbl_Employees[],5,FALSE)="Hourly", VLOOKUP(A8,tbl_Employees[],6,FALSE)*1.5*VLOOKUP(A8,tbl_Timesheet[],4,FALSE), 0) -> 54 | E8: =C8+D8 -> 1014 | F8: =MAX(0,MIN((E8-67.31)*0.0595,67.58)) -> 56.328055 | G8: =MIN(E8*0.0166,20.19) -> 16.8324 | H8: =IF(E8>735,E8*0.15,E8*0.05) -> 152.1 | I8: =IF(E8>735,E8*0.0505,E8*0.02) -> 51.207 | J8: =SUM(F8:I8) -> 276.46745 | K8: =E8-J8 -> 737.53255
A9: =tbl_Timesheet[[#This Row],[Emp_ID]] -> E008 | B9: =VLOOKUP(A9,tbl_Employees[],3,FALSE)&" "&VLOOKUP(A9,tbl_Employees[],2,FALSE) -> Ana Rodriguez | C9: =IF(VLOOKUP(A9,tbl_Employees[],5,FALSE)="Hourly", VLOOKUP(A9,tbl_Employees[],6,FALSE)*VLOOKUP(A9,tbl_Timesheet[],3,FALSE), VLOOKUP(A9,tbl_Employees[],7,FALSE)/26) -> 3269.2308 | D9: =IF(VLOOKUP(A9,tbl_Employees[],5,FALSE)="Hourly", VLOOKUP(A9,tbl_Employees[],6,FALSE)*1.5*VLOOKUP(A9,tbl_Timesheet[],4,FALSE), 0) -> 0 | E9: =C9+D9 -> 3269.2308 | F9: =MAX(0,MIN((E9-67.31)*0.0595,67.58)) -> 67.58 | G9: =MIN(E9*0.0166,20.19) -> 20.19 | H9: =IF(E9>735,E9*0.15,E9*0.05) -> 490.38462 | I9: =IF(E9>735,E9*0.0505,E9*0.02) -> 165.09615 | J9: =SUM(F9:I9) -> 743.25077 | K9: =E9-J9 -> 2525.98
A10: =tbl_Timesheet[[#This Row],[Emp_ID]] -> E009 | B10: =VLOOKUP(A10,tbl_Employees[],3,FALSE)&" "&VLOOKUP(A10,tbl_Employees[],2,FALSE) -> James Wilson | C10: =IF(VLOOKUP(A10,tbl_Employees[],5,FALSE)="Hourly", VLOOKUP(A10,tbl_Employees[],6,FALSE)*VLOOKUP(A10,tbl_Timesheet[],3,FALSE), VLOOKUP(A10,tbl_Employees[],7,FALSE)/26) -> 893 | D10: =IF(VLOOKUP(A10,tbl_Employees[],5,FALSE)="Hourly", VLOOKUP(A10,tbl_Employees[],6,FALSE)*1.5*VLOOKUP(A10,tbl_Timesheet[],4,FALSE), 0) -> 0 | E10: =C10+D10 -> 893 | F10: =MAX(0,MIN((E10-67.31)*0.0595,67.58)) -> 49.128555 | G10: =MIN(E10*0.0166,20.19) -> 14.8238 | H10: =IF(E10>735,E10*0.15,E10*0.05) -> 133.95 | I10: =IF(E10>735,E10*0.0505,E10*0.02) -> 45.0965 | J10: =SUM(F10:I10) -> 242.99885 | K10: =E10-J10 -> 650.00114
A11: =tbl_Timesheet[[#This Row],[Emp_ID]] -> E010 | B11: =VLOOKUP(A11,tbl_Employees[],3,FALSE)&" "&VLOOKUP(A11,tbl_Employees[],2,FALSE) -> Sofia Lopez | C11: =IF(VLOOKUP(A11,tbl_Employees[],5,FALSE)="Hourly", VLOOKUP(A11,tbl_Employees[],6,FALSE)*VLOOKUP(A11,tbl_Timesheet[],3,FALSE), VLOOKUP(A11,tbl_Employees[],7,FALSE)/26) -> 1080 | D11: =IF(VLOOKUP(A11,tbl_Employees[],5,FALSE)="Hourly", VLOOKUP(A11,tbl_Employees[],6,FALSE)*1.5*VLOOKUP(A11,tbl_Timesheet[],4,FALSE), 0) -> 243 | E11: =C11+D11 -> 1323 | F11: =MAX(0,MIN((E11-67.31)*0.0595,67.58)) -> 67.58 | G11: =MIN(E11*0.0166,20.19) -> 20.19 | H11: =IF(E11>735,E11*0.15,E11*0.05) -> 198.45 | I11: =IF(E11>735,E11*0.0505,E11*0.02) -> 66.8115 | J11: =SUM(F11:I11) -> 353.0315 | K11: =E11-J11 -> 969.9685
A12: =tbl_Timesheet[[#This Row],[Emp_ID]] -> E011 | B12: =VLOOKUP(A12,tbl_Employees[],3,FALSE)&" "&VLOOKUP(A12,tbl_Employees[],2,FALSE) -> Kevin Lee | C12: =IF(VLOOKUP(A12,tbl_Employees[],5,FALSE)="Hourly", VLOOKUP(A12,tbl_Employees[],6,FALSE)*VLOOKUP(A12,tbl_Timesheet[],3,FALSE), VLOOKUP(A12,tbl_Employees[],7,FALSE)/26) -> 860 | D12: =IF(VLOOKUP(A12,tbl_Employees[],5,FALSE)="Hourly", VLOOKUP(A12,tbl_Employees[],6,FALSE)*1.5*VLOOKUP(A12,tbl_Timesheet[],4,FALSE), 0) -> 0 | E12: =C12+D12 -> 860 | F12: =MAX(0,MIN((E12-67.31)*0.0595,67.58)) -> 47.165055 | G12: =MIN(E12*0.0166,20.19) -> 14.276 | H12: =IF(E12>735,E12*0.15,E12*0.05) -> 129 | I12: =IF(E12>735,E12*0.0505,E12*0.02) -> 43.43 | J12: =SUM(F12:I12) -> 233.87106 | K12: =E12-J12 -> 626.12894
A13: =tbl_Timesheet[[#This Row],[Emp_ID]] -> E012 | B13: =VLOOKUP(A13,tbl_Employees[],3,FALSE)&" "&VLOOKUP(A13,tbl_Employees[],2,FALSE) -> Lisa Walker | C13: =IF(VLOOKUP(A13,tbl_Employees[],5,FALSE)="Hourly", VLOOKUP(A13,tbl_Employees[],6,FALSE)*VLOOKUP(A13,tbl_Timesheet[],3,FALSE), VLOOKUP(A13,tbl_Employees[],7,FALSE)/26) -> 2884.6154 | D13: =IF(VLOOKUP(A13,tbl_Employees[],5,FALSE)="Hourly", VLOOKUP(A13,tbl_Employees[],6,FALSE)*1.5*VLOOKUP(A13,tbl_Timesheet[],4,FALSE), 0) -> 0 | E13: =C13+D13 -> 2884.6154 | F13: =MAX(0,MIN((E13-67.31)*0.0595,67.58)) -> 67.58 | G13: =MIN(E13*0.0166,20.19) -> 20.19 | H13: =IF(E13>735,E13*0.15,E13*0.05) -> 432.69231 | I13: =IF(E13>735,E13*0.0505,E13*0.02) -> 145.67308 | J13: =SUM(F13:I13) -> 666.13538 | K13: =E13-J13 -> 2218.48
... A31: =tbl_Timesheet[[#This Row],[Emp_ID]] -> E030 | B31: =VLOOKUP(A31,tbl_Employees[],3,FALSE)&" "&VLOOKUP(A31,tbl_Employees[],2,FALSE) -> Megan Evans | C31: =IF(VLOOKUP(A31,tbl_Employees[],5,FALSE)="Hourly", VLOOKUP(A31,tbl_Employees[],6,FALSE)*VLOOKUP(A31,tbl_Timesheet[],3,FALSE), VLOOKUP(A31,tbl_Employees[],7,FALSE)/26) -> 1120 | D31: =IF(VLOOKUP(A31,tbl_Employees[],5,FALSE)="Hourly", VLOOKUP(A31,tbl_Employees[],6,FALSE)*1.5*VLOOKUP(A31,tbl_Timesheet[],4,FALSE), 0) -> 168 | E31: =C31+D31 -> 1288 | F31: =MAX(0,MIN((E31-67.31)*0.0595,67.58)) -> 67.58 | G31: =MIN(E31*0.0166,20.19) -> 20.19 | H31: =IF(E31>735,E31*0.15,E31*0.05) -> 193.2 | I31: =IF(E31>735,E31*0.0505,E31*0.02) -> 65.044 | J31: =SUM(F31:I31) -> 346.014 | K31: =E31-J31 -> 941.986
A33: Payroll Summary for Journal Entry
A34: Description | B34: Amount
A35: Total Gross Pay | B35: =SUM(Table3[Gross_Pay]) -> 45259.683
A36: Total CPP | B36: =SUM(Table3[CPP]) -> 1820.6375
A37: Total EI | B37: =SUM(Table3[EI]) -> 544.50815
A38: Total Income Tax | B38: =SUM(H2:I31) -> 9074.5664
A39: Total Deductions | B39: =SUM(Table3[Total_Deductions]) -> 11439.712
A40: Total Net Pay | B40: =SUM(Table3[Net_Pay]) -> 33819.971

Sheet JE_Payroll
A2: Date | B2: Account | C2: Account_Name | D2: Debit | E2: Credit | F2: Memo
A3: 45639 | B3: 5100 | C3: Wages Expense | D3: =Payroll_Calc!B35 -> 45259.683 | F3: Payroll week ending 12/13/24
A4: 45639 | B4: 2200 | C4: CPP Payable | E4: =Payroll_Calc!B36 -> 1820.6375 | F4: Employee CPP withheld
A5: 45639 | B5: 2200 | C5: EI Payable | E5: =Payroll_Calc!B37 -> 544.50815 | F5: Employee EI withheld
A6: 45639 | B6: 2200 | C6: Income Tax Payable | E6: =Payroll_Calc!B38 -> 9074.5664 | F6: Income tax withheld
A7: 45639 | B7: 1000 | C7: Total Deductions | E7: =Payroll_Calc!B39 -> 11439.712 | F7: Total Deductions
A8: 45640 | B8: 1000 | C8: Cash - Payroll | E8: =Payroll_Calc!B40 -> 33819.971 | F8: Net pay deposited
