Workbook

Sheet 10 Trial Balance 
A1: Account_No | B1: Account_Name | C1: Unadjusted_Debit | D1: Unadjusted_Credit | E1: Adjustments_Debit | F1: Adjustments_Credit | G1: Adjusted_Debit | H1: Adjusted_Credit | I1: HST_Eligible | J1: ITC_Amount
A2: ASSETS | G2: =IF(ABS(IF(Table3[[#This Row],[Unadjusted_Debit]]>=0,Table3[[#This Row],[Unadjusted_Debit]]+Table3[[#This Row],[Adjustments_Debit]]-Table3[[#This Row],[Adjustments_Credit]],"0"))=0,"",(ABS(IF(Table3[[#This Row],[Unadjusted_Debit]]>=0,Table3[[#This Row],[Unadjusted_Debit]]+Table3[[#This Row],[Adjustments_Debit]]-Table3[[#This Row],[Adjustments_Credit]],"0")))) | H2: =IF(Table3[[#This Row],[Unadjusted_Credit]]>0,Table3[[#This Row],[Unadjusted_Credit]]+Table3[[#This Row],[Adjustments_Credit]]-Table3[[#This Row],[Adjustments_Debit]],"") | J2: =IF(Table3[[#This Row],[HST_Eligible]]="YES",Table3[[#This Row],[Adjusted_Debit]]*0.13,IF(Table3[[#This Row],[Adjusted_Debit]]="Partial",Table3[[#Headers],[Adjusted_Debit]]*0.13*0.5,IF(Table3[[#This Row],[HST_Eligible]]="NO",0,"")))
A3: 1000 | B3: Cash | C3: 82875.5 | F3: 375 | G3: =IF(ABS(IF(Table3[[#This Row],[Unadjusted_Debit]]>=0,Table3[[#This Row],[Unadjusted_Debit]]+Table3[[#This Row],[Adjustments_Debit]]-Table3[[#This Row],[Adjustments_Credit]],"0"))=0,"",(ABS(IF(Table3[[#This Row],[Unadjusted_Debit]]>=0,Table3[[#This Row],[Unadjusted_Debit]]+Table3[[#This Row],[Adjustments_Debit]]-Table3[[#This Row],[Adjustments_Credit]],"0")))) -> 82500.5 | H3: =IF(Table3[[#This Row],[Unadjusted_Credit]]>0,Table3[[#This Row],[Unadjusted_Credit]]+Table3[[#This Row],[Adjustments_Credit]]-Table3[[#This Row],[Adjustments_Debit]],"") | I3: N/A | J3: =IF(Table3[[#This Row],[HST_Eligible]]="YES",Table3[[#This Row],[Adjusted_Debit]]*0.13,IF(Table3[[#This Row],[Adjusted_Debit]]="Partial",Table3[[#Headers],[Adjusted_Debit]]*0.13*0.5,IF(Table3[[#This Row],[HST_Eligible]]="NO",0,"")))
A4: 1010 | B4: Petty Cash | C4: 500 | G4: =IF(ABS(IF(Table3[[#This Row],[Unadjusted_Debit]]>=0,Table3[[#This Row],[Unadjusted_Debit]]+Table3[[#This Row],[Adjustments_Debit]]-Table3[[#This Row],[Adjustments_Credit]],"0"))=0,"",(ABS(IF(Table3[[#This Row],[Unadjusted_Debit]]>=0,Table3[[#This Row],[Unadjusted_Debit]]+Table3[[#This Row],[Adjustments_Debit]]-Table3[[#This Row],[Adjustments_Credit]],"0")))) -> 500 | H4: =IF(Table3[[#This Row],[Unadjusted_Credit]]>0,Table3[[#This Row],[Unadjusted_Credit]]+Table3[[#This Row],[Adjustments_Credit]]-Table3[[#This Row],[Adjustments_Debit]],"") | I4: N/A | J4: =IF(Table3[[#This Row],[HST_Eligible]]="YES",Table3[[#This Row],[Adjusted_Debit]]*0.13,IF(Table3[[#This Row],[Adjusted_Debit]]="Partial",Table3[[#Headers],[Adjusted_Debit]]*0.13*0.5,IF(Table3[[#This Row],[HST_Eligible]]="NO",0,"")))
A5: 1100 | B5: Accounts Receivable | C5: 715200 | E5: 350 | G5: =IF(ABS(IF(Table3[[#This Row],[Unadjusted_Debit]]>=0,Table3[[#This Row],[Unadjusted_Debit]]+Table3[[#This Row],[Adjustments_Debit]]-Table3[[#This Row],[Adjustments_Credit]],"0"))=0,"",(ABS(IF(Table3[[#This Row],[Unadjusted_Debit]]>=0,Table3[[#This Row],[Unadjusted_Debit]]+Table3[[#This Row],[Adjustments_Debit]]-Table3[[#This Row],[Adjustments_Credit]],"0")))) -> 715550 | H5: =IF(Table3[[#This Row],[Unadjusted_Credit]]>0,Table3[[#This Row],[Unadjusted_Credit]]+Table3[[#This Row],[Adjustments_Credit]]-Table3[[#This Row],[Adjustments_Debit]],"") | I5: N/A | J5: =IF(Table3[[#This Row],[HST_Eligible]]="YES",Table3[[#This Row],[Adjusted_Debit]]*0.13,IF(Table3[[#This Row],[Adjusted_Debit]]="Partial",Table3[[#Headers],[Adjusted_Debit]]*0.13*0.5,IF(Table3[[#This Row],[HST_Eligible]]="NO",0,"")))
A6: 1110 | B6: Allowance for Doubtful Accounts | D6: 12000 | F6: 652 | G6: =IF(ABS(IF(Table3[[#This Row],[Unadjusted_Debit]]>=0,Table3[[#This Row],[Unadjusted_Debit]]+Table3[[#This Row],[Adjustments_Debit]]-Table3[[#This Row],[Adjustments_Credit]],"0"))=0,"",(ABS(IF(Table3[[#This Row],[Unadjusted_Debit]]>=0,Table3[[#This Row],[Unadjusted_Debit]]+Table3[[#This Row],[Adjustments_Debit]]-Table3[[#This Row],[Adjustments_Credit]],"0")))) -> 652 | H6: =IF(Table3[[#This Row],[Unadjusted_Credit]]>0,Table3[[#This Row],[Unadjusted_Credit]]+Table3[[#This Row],[Adjustments_Credit]]-Table3[[#This Row],[Adjustments_Debit]],"") -> 12652 | I6: N/A | J6: =IF(Table3[[#This Row],[HST_Eligible]]="YES",Table3[[#This Row],[Adjusted_Debit]]*0.13,IF(Table3[[#This Row],[Adjusted_Debit]]="Partial",Table3[[#Headers],[Adjusted_Debit]]*0.13*0.5,IF(Table3[[#This Row],[HST_Eligible]]="NO",0,"")))
A7: 1200 | B7: Inventory - New Vehicles | C7: 450000 | F7: 800 | G7: =IF(ABS(IF(Table3[[#This Row],[Unadjusted_Debit]]>=0,Table3[[#This Row],[Unadjusted_Debit]]+Table3[[#This Row],[Adjustments_Debit]]-Table3[[#This Row],[Adjustments_Credit]],"0"))=0,"",(ABS(IF(Table3[[#This Row],[Unadjusted_Debit]]>=0,Table3[[#This Row],[Unadjusted_Debit]]+Table3[[#This Row],[Adjustments_Debit]]-Table3[[#This Row],[Adjustments_Credit]],"0")))) -> 449200 | H7: =IF(Table3[[#This Row],[Unadjusted_Credit]]>0,Table3[[#This Row],[Unadjusted_Credit]]+Table3[[#This Row],[Adjustments_Credit]]-Table3[[#This Row],[Adjustments_Debit]],"") | I7: N/A | J7: =IF(Table3[[#This Row],[HST_Eligible]]="YES",Table3[[#This Row],[Adjusted_Debit]]*0.13,IF(Table3[[#This Row],[Adjusted_Debit]]="Partial",Table3[[#Headers],[Adjusted_Debit]]*0.13*0.5,IF(Table3[[#This Row],[HST_Eligible]]="NO",0,"")))
A8: 1210 | B8: Inventory - Used Vehicles | C8: 125000 | G8: =IF(ABS(IF(Table3[[#This Row],[Unadjusted_Debit]]>=0,Table3[[#This Row],[Unadjusted_Debit]]+Table3[[#This Row],[Adjustments_Debit]]-Table3[[#This Row],[Adjustments_Credit]],"0"))=0,"",(ABS(IF(Table3[[#This Row],[Unadjusted_Debit]]>=0,Table3[[#This Row],[Unadjusted_Debit]]+Table3[[#This Row],[Adjustments_Debit]]-Table3[[#This Row],[Adjustments_Credit]],"0")))) -> 125000 | H8: =IF(Table3[[#This Row],[Unadjusted_Credit]]>0,Table3[[#This Row],[Unadjusted_Credit]]+Table3[[#This Row],[Adjustments_Credit]]-Table3[[#This Row],[Adjustments_Debit]],"") | I8: N/A | J8: =IF(Table3[[#This Row],[HST_Eligible]]="YES",Table3[[#This Row],[Adjusted_Debit]]*0.13,IF(Table3[[#This Row],[Adjusted_Debit]]="Partial",Table3[[#Headers],[Adjusted_Debit]]*0.13*0.5,IF(Table3[[#This Row],[HST_Eligible]]="NO",0,"")))
A9: 1220 | B9: Inventory - Parts | C9: 45600 | G9: =IF(ABS(IF(Table3[[#This Row],[Unadjusted_Debit]]>=0,Table3[[#This Row],[Unadjusted_Debit]]+Table3[[#This Row],[Adjustments_Debit]]-Table3[[#This Row],[Adjustments_Credit]],"0"))=0,"",(ABS(IF(Table3[[#This Row],[Unadjusted_Debit]]>=0,Table3[[#This Row],[Unadjusted_Debit]]+Table3[[#This Row],[Adjustments_Debit]]-Table3[[#This Row],[Adjustments_Credit]],"0")))) -> 45600 | H9: =IF(Table3[[#This Row],[Unadjusted_Credit]]>0,Table3[[#This Row],[Unadjusted_Credit]]+Table3[[#This Row],[Adjustments_Credit]]-Table3[[#This Row],[Adjustments_Debit]],"") | I9: N/A | J9: =IF(Table3[[#This Row],[HST_Eligible]]="YES",Table3[[#This Row],[Adjusted_Debit]]*0.13,IF(Table3[[#This Row],[Adjusted_Debit]]="Partial",Table3[[#Headers],[Adjusted_Debit]]*0.13*0.5,IF(Table3[[#This Row],[HST_Eligible]]="NO",0,"")))
A10: 1300 | B10: Prepaid Insurance | C10: 7200 | F10: 600 | G10: =IF(ABS(IF(Table3[[#This Row],[Unadjusted_Debit]]>=0,Table3[[#This Row],[Unadjusted_Debit]]+Table3[[#This Row],[Adjustments_Debit]]-Table3[[#This Row],[Adjustments_Credit]],"0"))=0,"",(ABS(IF(Table3[[#This Row],[Unadjusted_Debit]]>=0,Table3[[#This Row],[Unadjusted_Debit]]+Table3[[#This Row],[Adjustments_Debit]]-Table3[[#This Row],[Adjustments_Credit]],"0")))) -> 6600 | H10: =IF(Table3[[#This Row],[Unadjusted_Credit]]>0,Table3[[#This Row],[Unadjusted_Credit]]+Table3[[#This Row],[Adjustments_Credit]]-Table3[[#This Row],[Adjustments_Debit]],"") | I10: N/A | J10: =IF(Table3[[#This Row],[HST_Eligible]]="YES",Table3[[#This Row],[Adjusted_Debit]]*0.13,IF(Table3[[#This Row],[Adjusted_Debit]]="Partial",Table3[[#Headers],[Adjusted_Debit]]*0.13*0.5,IF(Table3[[#This Row],[HST_Eligible]]="NO",0,"")))
A11: 1400 | B11: Property, Plant & Equipment | C11: 250000 | G11: =IF(ABS(IF(Table3[[#This Row],[Unadjusted_Debit]]>=0,Table3[[#This Row],[Unadjusted_Debit]]+Table3[[#This Row],[Adjustments_Debit]]-Table3[[#This Row],[Adjustments_Credit]],"0"))=0,"",(ABS(IF(Table3[[#This Row],[Unadjusted_Debit]]>=0,Table3[[#This Row],[Unadjusted_Debit]]+Table3[[#This Row],[Adjustments_Debit]]-Table3[[#This Row],[Adjustments_Credit]],"0")))) -> 250000 | H11: =IF(Table3[[#This Row],[Unadjusted_Credit]]>0,Table3[[#This Row],[Unadjusted_Credit]]+Table3[[#This Row],[Adjustments_Credit]]-Table3[[#This Row],[Adjustments_Debit]],"") | I11: N/A | J11: =IF(Table3[[#This Row],[HST_Eligible]]="YES",Table3[[#This Row],[Adjusted_Debit]]*0.13,IF(Table3[[#This Row],[Adjusted_Debit]]="Partial",Table3[[#Headers],[Adjusted_Debit]]*0.13*0.5,IF(Table3[[#This Row],[HST_Eligible]]="NO",0,"")))
A12: 1410 | B12: Accumulated Depreciation | D12: 95000 | F12: 3750 | G12: =IF(ABS(IF(Table3[[#This Row],[Unadjusted_Debit]]>=0,Table3[[#This Row],[Unadjusted_Debit]]+Table3[[#This Row],[Adjustments_Debit]]-Table3[[#This Row],[Adjustments_Credit]],"0"))=0,"",(ABS(IF(Table3[[#This Row],[Unadjusted_Debit]]>=0,Table3[[#This Row],[Unadjusted_Debit]]+Table3[[#This Row],[Adjustments_Debit]]-Table3[[#This Row],[Adjustments_Credit]],"0")))) -> 3750 | H12: =IF(Table3[[#This Row],[Unadjusted_Credit]]>0,Table3[[#This Row],[Unadjusted_Credit]]+Table3[[#This Row],[Adjustments_Credit]]-Table3[[#This Row],[Adjustments_Debit]],"") -> 98750 | I12: N/A | J12: =IF(Table3[[#This Row],[HST_Eligible]]="YES",Table3[[#This Row],[Adjusted_Debit]]*0.13,IF(Table3[[#This Row],[Adjusted_Debit]]="Partial",Table3[[#Headers],[Adjusted_Debit]]*0.13*0.5,IF(Table3[[#This Row],[HST_Eligible]]="NO",0,"")))
G13: =IF(ABS(IF(Table3[[#This Row],[Unadjusted_Debit]]>=0,Table3[[#This Row],[Unadjusted_Debit]]+Table3[[#This Row],[Adjustments_Debit]]-Table3[[#This Row],[Adjustments_Credit]],"0"))=0,"",(ABS(IF(Table3[[#This Row],[Unadjusted_Debit]]>=0,Table3[[#This Row],[Unadjusted_Debit]]+Table3[[#This Row],[Adjustments_Debit]]-Table3[[#This Row],[Adjustments_Credit]],"0")))) | H13: =IF(Table3[[#This Row],[Unadjusted_Credit]]>0,Table3[[#This Row],[Unadjusted_Credit]]+Table3[[#This Row],[Adjustments_Credit]]-Table3[[#This Row],[Adjustments_Debit]],"") | J13: =IF(Table3[[#This Row],[HST_Eligible]]="YES",Table3[[#This Row],[Adjusted_Debit]]*0.13,IF(Table3[[#This Row],[Adjusted_Debit]]="Partial",Table3[[#Headers],[Adjusted_Debit]]*0.13*0.5,IF(Table3[[#This Row],[HST_Eligible]]="NO",0,"")))
A14: LIABILITIES | G14: =IF(ABS(IF(Table3[[#This Row],[Unadjusted_Debit]]>=0,Table3[[#This Row],[Unadjusted_Debit]]+Table3[[#This Row],[Adjustments_Debit]]-Table3[[#This Row],[Adjustments_Credit]],"0"))=0,"",(ABS(IF(Table3[[#This Row],[Unadjusted_Debit]]>=0,Table3[[#This Row],[Unadjusted_Debit]]+Table3[[#This Row],[Adjustments_Debit]]-Table3[[#This Row],[Adjustments_Credit]],"0")))) | H14: =IF(Table3[[#This Row],[Unadjusted_Credit]]>0,Table3[[#This Row],[Unadjusted_Credit]]+Table3[[#This Row],[Adjustments_Credit]]-Table3[[#This Row],[Adjustments_Debit]],"") | J14: =IF(Table3[[#This Row],[HST_Eligible]]="YES",Table3[[#This Row],[Adjusted_Debit]]*0.13,IF(Table3[[#This Row],[Adjusted_Debit]]="Partial",Table3[[#Headers],[Adjusted_Debit]]*0.13*0.5,IF(Table3[[#This Row],[HST_Eligible]]="NO",0,"")))
A15: 2000 | B15: Accounts Payable | D15: 125300 | G15: =IF(ABS(IF(Table3[[#This Row],[Unadjusted_Debit]]>=0,Table3[[#This Row],[Unadjusted_Debit]]+Table3[[#This Row],[Adjustments_Debit]]-Table3[[#This Row],[Adjustments_Credit]],"0"))=0,"",(ABS(IF(Table3[[#This Row],[Unadjusted_Debit]]>=0,Table3[[#This Row],[Unadjusted_Debit]]+Table3[[#This Row],[Adjustments_Debit]]-Table3[[#This Row],[Adjustments_Credit]],"0")))) | H15: =IF(Table3[[#This Row],[Unadjusted_Credit]]>0,Table3[[#This Row],[Unadjusted_Credit]]+Table3[[#This Row],[Adjustments_Credit]]-Table3[[#This Row],[Adjustments_Debit]],"") -> 125300 | I15: N/A | J15: =IF(Table3[[#This Row],[HST_Eligible]]="YES",Table3[[#This Row],[Adjusted_Debit]]*0.13,IF(Table3[[#This Row],[Adjusted_Debit]]="Partial",Table3[[#Headers],[Adjusted_Debit]]*0.13*0.5,IF(Table3[[#This Row],[HST_Eligible]]="NO",0,"")))
A16: 2010 | B16: Credit Card Payable | D16: 5372 | G16: =IF(ABS(IF(Table3[[#This Row],[Unadjusted_Debit]]>=0,Table3[[#This Row],[Unadjusted_Debit]]+Table3[[#This Row],[Adjustments_Debit]]-Table3[[#This Row],[Adjustments_Credit]],"0"))=0,"",(ABS(IF(Table3[[#This Row],[Unadjusted_Debit]]>=0,Table3[[#This Row],[Unadjusted_Debit]]+Table3[[#This Row],[Adjustments_Debit]]-Table3[[#This Row],[Adjustments_Credit]],"0")))) | H16: =IF(Table3[[#This Row],[Unadjusted_Credit]]>0,Table3[[#This Row],[Unadjusted_Credit]]+Table3[[#This Row],[Adjustments_Credit]]-Table3[[#This Row],[Adjustments_Debit]],"") -> 5372 | I16: N/A | J16: =IF(Table3[[#This Row],[HST_Eligible]]="YES",Table3[[#This Row],[Adjusted_Debit]]*0.13,IF(Table3[[#This Row],[Adjusted_Debit]]="Partial",Table3[[#Headers],[Adjusted_Debit]]*0.13*0.5,IF(Table3[[#This Row],[HST_Eligible]]="NO",0,"")))
A17: 2100 | B17: HST Payable | D17: 16900 | G17: =IF(ABS(IF(Table3[[#This Row],[Unadjusted_Debit]]>=0,Table3[[#This Row],[Unadjusted_Debit]]+Table3[[#This Row],[Adjustments_Debit]]-Table3[[#This Row],[Adjustments_Credit]],"0"))=0,"",(ABS(IF(Table3[[#This Row],[Unadjusted_Debit]]>=0,Table3[[#This Row],[Unadjusted_Debit]]+Table3[[#This Row],[Adjustments_Debit]]-Table3[[#This Row],[Adjustments_Credit]],"0")))) | H17: =IF(Table3[[#This Row],[Unadjusted_Credit]]>0,Table3[[#This Row],[Unadjusted_Credit]]+Table3[[#This Row],[Adjustments_Credit]]-Table3[[#This Row],[Adjustments_Debit]],"") -> 16900 | I17: N/A | J17: =IF(Table3[[#This Row],[HST_Eligible]]="YES",Table3[[#This Row],[Adjusted_Debit]]*0.13,IF(Table3[[#This Row],[Adjusted_Debit]]="Partial",Table3[[#Headers],[Adjusted_Debit]]*0.13*0.5,IF(Table3[[#This Row],[HST_Eligible]]="NO",0,"")))
A18: 2200 | B18: Payroll Liabilities | D18: 18450 | E18: 3400 | G18: =IF(ABS(IF(Table3[[#This Row],[Unadjusted_Debit]]>=0,Table3[[#This Row],[Unadjusted_Debit]]+Table3[[#This Row],[Adjustments_Debit]]-Table3[[#This Row],[Adjustments_Credit]],"0"))=0,"",(ABS(IF(Table3[[#This Row],[Unadjusted_Debit]]>=0,Table3[[#This Row],[Unadjusted_Debit]]+Table3[[#This Row],[Adjustments_Debit]]-Table3[[#This Row],[Adjustments_Credit]],"0")))) -> 3400 | H18: =Table3[[#This Row],[Adjusted_Debit]]+Table3[[#This Row],[Unadjusted_Credit]] -> 21850 | I18: N/A | J18: =IF(Table3[[#This Row],[HST_Eligible]]="YES",Table3[[#This Row],[Adjusted_Debit]]*0.13,IF(Table3[[#This Row],[Adjusted_Debit]]="Partial",Table3[[#Headers],[Adjusted_Debit]]*0.13*0.5,IF(Table3[[#This Row],[HST_Eligible]]="NO",0,"")))
A19: 2300 | B19: Interest Payable | D19: 0 | F19: 400 | G19: =IF(ABS(IF(Table3[[#This Row],[Unadjusted_Debit]]>=0,Table3[[#This Row],[Unadjusted_Debit]]+Table3[[#This Row],[Adjustments_Debit]]-Table3[[#This Row],[Adjustments_Credit]],"0"))=0,"",(ABS(IF(Table3[[#This Row],[Unadjusted_Debit]]>=0,Table3[[#This Row],[Unadjusted_Debit]]+Table3[[#This Row],[Adjustments_Debit]]-Table3[[#This Row],[Adjustments_Credit]],"0")))) -> 400 | H19: 400 | I19: N/A | J19: =IF(Table3[[#This Row],[HST_Eligible]]="YES",Table3[[#This Row],[Adjusted_Debit]]*0.13,IF(Table3[[#This Row],[Adjusted_Debit]]="Partial",Table3[[#Headers],[Adjusted_Debit]]*0.13*0.5,IF(Table3[[#This Row],[HST_Eligible]]="NO",0,"")))
A20: 2400 | B20: Long-term Debt | D20: 80000 | G20: =IF(ABS(IF(Table3[[#This Row],[Unadjusted_Debit]]>=0,Table3[[#This Row],[Unadjusted_Debit]]+Table3[[#This Row],[Adjustments_Debit]]-Table3[[#This Row],[Adjustments_Credit]],"0"))=0,"",(ABS(IF(Table3[[#This Row],[Unadjusted_Debit]]>=0,Table3[[#This Row],[Unadjusted_Debit]]+Table3[[#This Row],[Adjustments_Debit]]-Table3[[#This Row],[Adjustments_Credit]],"0")))) | H20: =IF(Table3[[#This Row],[Unadjusted_Credit]]>0,Table3[[#This Row],[Unadjusted_Credit]]+Table3[[#This Row],[Adjustments_Credit]]-Table3[[#This Row],[Adjustments_Debit]],"") -> 80000 | I20: N/A | J20: =IF(Table3[[#This Row],[HST_Eligible]]="YES",Table3[[#This Row],[Adjusted_Debit]]*0.13,IF(Table3[[#This Row],[Adjusted_Debit]]="Partial",Table3[[#Headers],[Adjusted_Debit]]*0.13*0.5,IF(Table3[[#This Row],[HST_Eligible]]="NO",0,"")))
G21: =IF(ABS(IF(Table3[[#This Row],[Unadjusted_Debit]]>=0,Table3[[#This Row],[Unadjusted_Debit]]+Table3[[#This Row],[Adjustments_Debit]]-Table3[[#This Row],[Adjustments_Credit]],"0"))=0,"",(ABS(IF(Table3[[#This Row],[Unadjusted_Debit]]>=0,Table3[[#This Row],[Unadjusted_Debit]]+Table3[[#This Row],[Adjustments_Debit]]-Table3[[#This Row],[Adjustments_Credit]],"0")))) | H21: =IF(Table3[[#This Row],[Unadjusted_Credit]]>0,Table3[[#This Row],[Unadjusted_Credit]]+Table3[[#This Row],[Adjustments_Credit]]-Table3[[#This Row],[Adjustments_Debit]],"") | J21: =IF(Table3[[#This Row],[HST_Eligible]]="YES",Table3[[#This Row],[Adjusted_Debit]]*0.13,IF(Table3[[#This Row],[Adjusted_Debit]]="Partial",Table3[[#Headers],[Adjusted_Debit]]*0.13*0.5,IF(Table3[[#This Row],[HST_Eligible]]="NO",0,"")))
A22: EQUITY | G22: =IF(ABS(IF(Table3[[#This Row],[Unadjusted_Debit]]>=0,Table3[[#This Row],[Unadjusted_Debit]]+Table3[[#This Row],[Adjustments_Debit]]-Table3[[#This Row],[Adjustments_Credit]],"0"))=0,"",(ABS(IF(Table3[[#This Row],[Unadjusted_Debit]]>=0,Table3[[#This Row],[Unadjusted_Debit]]+Table3[[#This Row],[Adjustments_Debit]]-Table3[[#This Row],[Adjustments_Credit]],"0")))) | H22: =IF(Table3[[#This Row],[Unadjusted_Credit]]>0,Table3[[#This Row],[Unadjusted_Credit]]+Table3[[#This Row],[Adjustments_Credit]]-Table3[[#This Row],[Adjustments_Debit]],"") | J22: =IF(Table3[[#This Row],[HST_Eligible]]="YES",Table3[[#This Row],[Adjusted_Debit]]*0.13,IF(Table3[[#This Row],[Adjusted_Debit]]="Partial",Table3[[#Headers],[Adjusted_Debit]]*0.13*0.5,IF(Table3[[#This Row],[HST_Eligible]]="NO",0,"")))
A23: 3000 | B23: Owner's Equity | D23: 450000 | G23: =IF(ABS(IF(Table3[[#This Row],[Unadjusted_Debit]]>=0,Table3[[#This Row],[Unadjusted_Debit]]+Table3[[#This Row],[Adjustments_Debit]]-Table3[[#This Row],[Adjustments_Credit]],"0"))=0,"",(ABS(IF(Table3[[#This Row],[Unadjusted_Debit]]>=0,Table3[[#This Row],[Unadjusted_Debit]]+Table3[[#This Row],[Adjustments_Debit]]-Table3[[#This Row],[Adjustments_Credit]],"0")))) | H23: =IF(Table3[[#This Row],[Unadjusted_Credit]]>0,Table3[[#This Row],[Unadjusted_Credit]]+Table3[[#This Row],[Adjustments_Credit]]-Table3[[#This Row],[Adjustments_Debit]],"") -> 450000 | I23: N/A | J23: =IF(Table3[[#This Row],[HST_Eligible]]="YES",Table3[[#This Row],[Adjusted_Debit]]*0.13,IF(Table3[[#This Row],[Adjusted_Debit]]="Partial",Table3[[#Headers],[Adjusted_Debit]]*0.13*0.5,IF(Table3[[#This Row],[HST_Eligible]]="NO",0,"")))
G24: =IF(ABS(IF(Table3[[#This Row],[Unadjusted_Debit]]>=0,Table3[[#This Row],[Unadjusted_Debit]]+Table3[[#This Row],[Adjustments_Debit]]-Table3[[#This Row],[Adjustments_Credit]],"0"))=0,"",(ABS(IF(Table3[[#This Row],[Unadjusted_Debit]]>=0,Table3[[#This Row],[Unadjusted_Debit]]+Table3[[#This Row],[Adjustments_Debit]]-Table3[[#This Row],[Adjustments_Credit]],"0")))) | H24: =IF(Table3[[#This Row],[Unadjusted_Credit]]>0,Table3[[#This Row],[Unadjusted_Credit]]+Table3[[#This Row],[Adjustments_Credit]]-Table3[[#This Row],[Adjustments_Debit]],"") | J24: =IF(Table3[[#This Row],[HST_Eligible]]="YES",Table3[[#This Row],[Adjusted_Debit]]*0.13,IF(Table3[[#This Row],[Adjusted_Debit]]="Partial",Table3[[#Headers],[Adjusted_Debit]]*0.13*0.5,IF(Table3[[#This Row],[HST_Eligible]]="NO",0,"")))
A25: REVENUE | G25: =IF(ABS(IF(Table3[[#This Row],[Unadjusted_Debit]]>=0,Table3[[#This Row],[Unadjusted_Debit]]+Table3[[#This Row],[Adjustments_Debit]]-Table3[[#This Row],[Adjustments_Credit]],"0"))=0,"",(ABS(IF(Table3[[#This Row],[Unadjusted_Debit]]>=0,Table3[[#This Row],[Unadjusted_Debit]]+Table3[[#This Row],[Adjustments_Debit]]-Table3[[#This Row],[Adjustments_Credit]],"0")))) | H25: =IF(Table3[[#This Row],[Unadjusted_Credit]]>0,Table3[[#This Row],[Unadjusted_Credit]]+Table3[[#This Row],[Adjustments_Credit]]-Table3[[#This Row],[Adjustments_Debit]],"") | J25: =IF(Table3[[#This Row],[HST_Eligible]]="YES",Table3[[#This Row],[Adjusted_Debit]]*0.13,IF(Table3[[#This Row],[Adjusted_Debit]]="Partial",Table3[[#Headers],[Adjusted_Debit]]*0.13*0.5,IF(Table3[[#This Row],[HST_Eligible]]="NO",0,"")))
A26: 4000 | B26: Sales Revenue - New Vehicles | D26: 1250000 | E26: 180 | G26: =IF(ABS(IF(Table3[[#This Row],[Unadjusted_Debit]]>=0,Table3[[#This Row],[Unadjusted_Debit]]+Table3[[#This Row],[Adjustments_Debit]]-Table3[[#This Row],[Adjustments_Credit]],"0"))=0,"",(ABS(IF(Table3[[#This Row],[Unadjusted_Debit]]>=0,Table3[[#This Row],[Unadjusted_Debit]]+Table3[[#This Row],[Adjustments_Debit]]-Table3[[#This Row],[Adjustments_Credit]],"0")))) -> 180 | H26: =IF(Table3[[#This Row],[Unadjusted_Credit]]>0,Table3[[#This Row],[Unadjusted_Credit]]+Table3[[#This Row],[Adjustments_Credit]]-Table3[[#This Row],[Adjustments_Debit]],"") -> 1249820 | I26: N/A | J26: =IF(Table3[[#This Row],[HST_Eligible]]="YES",Table3[[#This Row],[Adjusted_Debit]]*0.13,IF(Table3[[#This Row],[Adjusted_Debit]]="Partial",Table3[[#Headers],[Adjusted_Debit]]*0.13*0.5,IF(Table3[[#This Row],[HST_Eligible]]="NO",0,"")))
A27: 4010 | B27: Sales Revenue - Used Vehicles | D27: 485000 | G27: =IF(ABS(IF(Table3[[#This Row],[Unadjusted_Debit]]>=0,Table3[[#This Row],[Unadjusted_Debit]]+Table3[[#This Row],[Adjustments_Debit]]-Table3[[#This Row],[Adjustments_Credit]],"0"))=0,"",(ABS(IF(Table3[[#This Row],[Unadjusted_Debit]]>=0,Table3[[#This Row],[Unadjusted_Debit]]+Table3[[#This Row],[Adjustments_Debit]]-Table3[[#This Row],[Adjustments_Credit]],"0")))) | H27: =IF(Table3[[#This Row],[Unadjusted_Credit]]>0,Table3[[#This Row],[Unadjusted_Credit]]+Table3[[#This Row],[Adjustments_Credit]]-Table3[[#This Row],[Adjustments_Debit]],"") -> 485000 | I27: N/A | J27: =IF(Table3[[#This Row],[HST_Eligible]]="YES",Table3[[#This Row],[Adjusted_Debit]]*0.13,IF(Table3[[#This Row],[Adjusted_Debit]]="Partial",Table3[[#Headers],[Adjusted_Debit]]*0.13*0.5,IF(Table3[[#This Row],[HST_Eligible]]="NO",0,"")))
A28: 4020 | B28: Service Revenue | D28: 325000 | G28: =IF(ABS(IF(Table3[[#This Row],[Unadjusted_Debit]]>=0,Table3[[#This Row],[Unadjusted_Debit]]+Table3[[#This Row],[Adjustments_Debit]]-Table3[[#This Row],[Adjustments_Credit]],"0"))=0,"",(ABS(IF(Table3[[#This Row],[Unadjusted_Debit]]>=0,Table3[[#This Row],[Unadjusted_Debit]]+Table3[[#This Row],[Adjustments_Debit]]-Table3[[#This Row],[Adjustments_Credit]],"0")))) | H28: =IF(Table3[[#This Row],[Unadjusted_Credit]]>0,Table3[[#This Row],[Unadjusted_Credit]]+Table3[[#This Row],[Adjustments_Credit]]-Table3[[#This Row],[Adjustments_Debit]],"") -> 325000 | I28: N/A | J28: =IF(Table3[[#This Row],[HST_Eligible]]="YES",Table3[[#This Row],[Adjusted_Debit]]*0.13,IF(Table3[[#This Row],[Adjusted_Debit]]="Partial",Table3[[#Headers],[Adjusted_Debit]]*0.13*0.5,IF(Table3[[#This Row],[HST_Eligible]]="NO",0,"")))
A29: 4030 | B29: Parts Revenue | D29: 158000 | G29: =IF(ABS(IF(Table3[[#This Row],[Unadjusted_Debit]]>=0,Table3[[#This Row],[Unadjusted_Debit]]+Table3[[#This Row],[Adjustments_Debit]]-Table3[[#This Row],[Adjustments_Credit]],"0"))=0,"",(ABS(IF(Table3[[#This Row],[Unadjusted_Debit]]>=0,Table3[[#This Row],[Unadjusted_Debit]]+Table3[[#This Row],[Adjustments_Debit]]-Table3[[#This Row],[Adjustments_Credit]],"0")))) | H29: =IF(Table3[[#This Row],[Unadjusted_Credit]]>0,Table3[[#This Row],[Unadjusted_Credit]]+Table3[[#This Row],[Adjustments_Credit]]-Table3[[#This Row],[Adjustments_Debit]],"") -> 158000 | I29: N/A | J29: =IF(Table3[[#This Row],[HST_Eligible]]="YES",Table3[[#This Row],[Adjusted_Debit]]*0.13,IF(Table3[[#This Row],[Adjusted_Debit]]="Partial",Table3[[#Headers],[Adjusted_Debit]]*0.13*0.5,IF(Table3[[#This Row],[HST_Eligible]]="NO",0,"")))
A31: COST OF GOODS SOLD | G31: =IF(ABS(IF(Table3[[#This Row],[Unadjusted_Debit]]>=0,Table3[[#This Row],[Unadjusted_Debit]]+Table3[[#This Row],[Adjustments_Debit]]-Table3[[#This Row],[Adjustments_Credit]],"0"))=0,"",(ABS(IF(Table3[[#This Row],[Unadjusted_Debit]]>=0,Table3[[#This Row],[Unadjusted_Debit]]+Table3[[#This Row],[Adjustments_Debit]]-Table3[[#This Row],[Adjustments_Credit]],"0")))) | H31: =IF(Table3[[#This Row],[Unadjusted_Credit]]>0,Table3[[#This Row],[Unadjusted_Credit]]+Table3[[#This Row],[Adjustments_Credit]]-Table3[[#This Row],[Adjustments_Debit]],"") | J31: =IF(Table3[[#This Row],[HST_Eligible]]="YES",Table3[[#This Row],[Adjusted_Debit]]*0.13,IF(Table3[[#This Row],[Adjusted_Debit]]="Partial",Table3[[#Headers],[Adjusted_Debit]]*0.13*0.5,IF(Table3[[#This Row],[HST_Eligible]]="NO",0,"")))
A32: 5000 | B32: COGS - New Vehicles | C32: 850000 | G32: =IF(ABS(IF(Table3[[#This Row],[Unadjusted_Debit]]>=0,Table3[[#This Row],[Unadjusted_Debit]]+Table3[[#This Row],[Adjustments_Debit]]-Table3[[#This Row],[Adjustments_Credit]],"0"))=0,"",(ABS(IF(Table3[[#This Row],[Unadjusted_Debit]]>=0,Table3[[#This Row],[Unadjusted_Debit]]+Table3[[#This Row],[Adjustments_Debit]]-Table3[[#This Row],[Adjustments_Credit]],"0")))) -> 850000 | I32: YES | J32: =IF(Table3[[#This Row],[HST_Eligible]]="YES",Table3[[#This Row],[Adjusted_Debit]]*0.13,IF(Table3[[#This Row],[Adjusted_Debit]]="Partial",Table3[[#Headers],[Adjusted_Debit]]*0.13*0.5,IF(Table3[[#This Row],[HST_Eligible]]="NO",0,""))) -> 110500
A33: 5001 | B33: COGS - Used Vehicles | C33: 275000 | G33: =IF(ABS(IF(Table3[[#This Row],[Unadjusted_Debit]]>=0,Table3[[#This Row],[Unadjusted_Debit]]+Table3[[#This Row],[Adjustments_Debit]]-Table3[[#This Row],[Adjustments_Credit]],"0"))=0,"",(ABS(IF(Table3[[#This Row],[Unadjusted_Debit]]>=0,Table3[[#This Row],[Unadjusted_Debit]]+Table3[[#This Row],[Adjustments_Debit]]-Table3[[#This Row],[Adjustments_Credit]],"0")))) -> 275000 | I33: YES | J33: =IF(Table3[[#This Row],[HST_Eligible]]="YES",Table3[[#This Row],[Adjusted_Debit]]*0.13,IF(Table3[[#This Row],[Adjusted_Debit]]="Partial",Table3[[#Headers],[Adjusted_Debit]]*0.13*0.5,IF(Table3[[#This Row],[HST_Eligible]]="NO",0,""))) -> 35750
A34: 5002 | B34: COGS - Parts | C34: 50000 | G34: =IF(ABS(IF(Table3[[#This Row],[Unadjusted_Debit]]>=0,Table3[[#This Row],[Unadjusted_Debit]]+Table3[[#This Row],[Adjustments_Debit]]-Table3[[#This Row],[Adjustments_Credit]],"0"))=0,"",(ABS(IF(Table3[[#This Row],[Unadjusted_Debit]]>=0,Table3[[#This Row],[Unadjusted_Debit]]+Table3[[#This Row],[Adjustments_Debit]]-Table3[[#This Row],[Adjustments_Credit]],"0")))) -> 50000 | I34: YES | J34: =IF(Table3[[#This Row],[HST_Eligible]]="YES",Table3[[#This Row],[Adjusted_Debit]]*0.13,IF(Table3[[#This Row],[Adjusted_Debit]]="Partial",Table3[[#Headers],[Adjusted_Debit]]*0.13*0.5,IF(Table3[[#This Row],[HST_Eligible]]="NO",0,""))) -> 6500
A35: 5003 | B35: Freight & Delivery | C35: 8000 | G35: =IF(ABS(IF(Table3[[#This Row],[Unadjusted_Debit]]>=0,Table3[[#This Row],[Unadjusted_Debit]]+Table3[[#This Row],[Adjustments_Debit]]-Table3[[#This Row],[Adjustments_Credit]],"0"))=0,"",(ABS(IF(Table3[[#This Row],[Unadjusted_Debit]]>=0,Table3[[#This Row],[Unadjusted_Debit]]+Table3[[#This Row],[Adjustments_Debit]]-Table3[[#This Row],[Adjustments_Credit]],"0")))) -> 8000 | I35: YES | J35: =IF(Table3[[#This Row],[HST_Eligible]]="YES",Table3[[#This Row],[Adjusted_Debit]]*0.13,IF(Table3[[#This Row],[Adjusted_Debit]]="Partial",Table3[[#Headers],[Adjusted_Debit]]*0.13*0.5,IF(Table3[[#This Row],[HST_Eligible]]="NO",0,""))) -> 1040
G36: =IF(ABS(IF(Table3[[#This Row],[Unadjusted_Debit]]>=0,Table3[[#This Row],[Unadjusted_Debit]]+Table3[[#This Row],[Adjustments_Debit]]-Table3[[#This Row],[Adjustments_Credit]],"0"))=0,"",(ABS(IF(Table3[[#This Row],[Unadjusted_Debit]]>=0,Table3[[#This Row],[Unadjusted_Debit]]+Table3[[#This Row],[Adjustments_Debit]]-Table3[[#This Row],[Adjustments_Credit]],"0")))) | J36: =IF(Table3[[#This Row],[HST_Eligible]]="YES",Table3[[#This Row],[Adjusted_Debit]]*0.13,IF(Table3[[#This Row],[Adjusted_Debit]]="Partial",Table3[[#Headers],[Adjusted_Debit]]*0.13*0.5,IF(Table3[[#This Row],[HST_Eligible]]="NO",0,"")))
A37: PAYROLL & BENEFITS | G37: =IF(ABS(IF(Table3[[#This Row],[Unadjusted_Debit]]>=0,Table3[[#This Row],[Unadjusted_Debit]]+Table3[[#This Row],[Adjustments_Debit]]-Table3[[#This Row],[Adjustments_Credit]],"0"))=0,"",(ABS(IF(Table3[[#This Row],[Unadjusted_Debit]]>=0,Table3[[#This Row],[Unadjusted_Debit]]+Table3[[#This Row],[Adjustments_Debit]]-Table3[[#This Row],[Adjustments_Credit]],"0")))) | J37: =IF(Table3[[#This Row],[HST_Eligible]]="YES",Table3[[#This Row],[Adjusted_Debit]]*0.13,IF(Table3[[#This Row],[Adjusted_Debit]]="Partial",Table3[[#Headers],[Adjusted_Debit]]*0.13*0.5,IF(Table3[[#This Row],[HST_Eligible]]="NO",0,"")))
A38: 5100 | B38: Salaries & Wages | C38: 285000 | E38: 3400 | G38: =IF(ABS(IF(Table3[[#This Row],[Unadjusted_Debit]]>=0,Table3[[#This Row],[Unadjusted_Debit]]+Table3[[#This Row],[Adjustments_Debit]]-Table3[[#This Row],[Adjustments_Credit]],"0"))=0,"",(ABS(IF(Table3[[#This Row],[Unadjusted_Debit]]>=0,Table3[[#This Row],[Unadjusted_Debit]]+Table3[[#This Row],[Adjustments_Debit]]-Table3[[#This Row],[Adjustments_Credit]],"0")))) -> 288400 | I38: NO | J38: =IF(Table3[[#This Row],[HST_Eligible]]="YES",Table3[[#This Row],[Adjusted_Debit]]*0.13,IF(Table3[[#This Row],[Adjusted_Debit]]="Partial",Table3[[#Headers],[Adjusted_Debit]]*0.13*0.5,IF(Table3[[#This Row],[HST_Eligible]]="NO",0,""))) -> 0
A39: 5105 | B39: Overtime Pay | C39: 5000 | G39: =IF(ABS(IF(Table3[[#This Row],[Unadjusted_Debit]]>=0,Table3[[#This Row],[Unadjusted_Debit]]+Table3[[#This Row],[Adjustments_Debit]]-Table3[[#This Row],[Adjustments_Credit]],"0"))=0,"",(ABS(IF(Table3[[#This Row],[Unadjusted_Debit]]>=0,Table3[[#This Row],[Unadjusted_Debit]]+Table3[[#This Row],[Adjustments_Debit]]-Table3[[#This Row],[Adjustments_Credit]],"0")))) -> 5000 | H39: =SUM(G38:G39) -> 293400 | I39: NO | J39: =IF(Table3[[#This Row],[HST_Eligible]]="YES",Table3[[#This Row],[Adjusted_Debit]]*0.13,IF(Table3[[#This Row],[Adjusted_Debit]]="Partial",Table3[[#Headers],[Adjusted_Debit]]*0.13*0.5,IF(Table3[[#This Row],[HST_Eligible]]="NO",0,""))) -> 0
A40: 5110 | B40: Employee Benefits - Health Insurance | C40: 18500 | G40: =IF(ABS(IF(Table3[[#This Row],[Unadjusted_Debit]]>=0,Table3[[#This Row],[Unadjusted_Debit]]+Table3[[#This Row],[Adjustments_Debit]]-Table3[[#This Row],[Adjustments_Credit]],"0"))=0,"",(ABS(IF(Table3[[#This Row],[Unadjusted_Debit]]>=0,Table3[[#This Row],[Unadjusted_Debit]]+Table3[[#This Row],[Adjustments_Debit]]-Table3[[#This Row],[Adjustments_Credit]],"0")))) -> 18500 | I40: NO | J40: =IF(Table3[[#This Row],[HST_Eligible]]="YES",Table3[[#This Row],[Adjusted_Debit]]*0.13,IF(Table3[[#This Row],[Adjusted_Debit]]="Partial",Table3[[#Headers],[Adjusted_Debit]]*0.13*0.5,IF(Table3[[#This Row],[HST_Eligible]]="NO",0,""))) -> 0
A41: 5115 | B41: Employee Benefits - Dental | C41: 6900 | G41: =IF(ABS(IF(Table3[[#This Row],[Unadjusted_Debit]]>=0,Table3[[#This Row],[Unadjusted_Debit]]+Table3[[#This Row],[Adjustments_Debit]]-Table3[[#This Row],[Adjustments_Credit]],"0"))=0,"",(ABS(IF(Table3[[#This Row],[Unadjusted_Debit]]>=0,Table3[[#This Row],[Unadjusted_Debit]]+Table3[[#This Row],[Adjustments_Debit]]-Table3[[#This Row],[Adjustments_Credit]],"0")))) -> 6900 | I41: NO | J41: =IF(Table3[[#This Row],[HST_Eligible]]="YES",Table3[[#This Row],[Adjusted_Debit]]*0.13,IF(Table3[[#This Row],[Adjusted_Debit]]="Partial",Table3[[#Headers],[Adjusted_Debit]]*0.13*0.5,IF(Table3[[#This Row],[HST_Eligible]]="NO",0,""))) -> 0
A42: 5120 | B42: CPP Employer Portion | C42: 14200 | G42: =IF(ABS(IF(Table3[[#This Row],[Unadjusted_Debit]]>=0,Table3[[#This Row],[Unadjusted_Debit]]+Table3[[#This Row],[Adjustments_Debit]]-Table3[[#This Row],[Adjustments_Credit]],"0"))=0,"",(ABS(IF(Table3[[#This Row],[Unadjusted_Debit]]>=0,Table3[[#This Row],[Unadjusted_Debit]]+Table3[[#This Row],[Adjustments_Debit]]-Table3[[#This Row],[Adjustments_Credit]],"0")))) -> 14200 | I42: NO | J42: =IF(Table3[[#This Row],[HST_Eligible]]="YES",Table3[[#This Row],[Adjusted_Debit]]*0.13,IF(Table3[[#This Row],[Adjusted_Debit]]="Partial",Table3[[#Headers],[Adjusted_Debit]]*0.13*0.5,IF(Table3[[#This Row],[HST_Eligible]]="NO",0,""))) -> 0
A43: 5125 | B43: EI Employer Portion | C43: 7300 | G43: =IF(ABS(IF(Table3[[#This Row],[Unadjusted_Debit]]>=0,Table3[[#This Row],[Unadjusted_Debit]]+Table3[[#This Row],[Adjustments_Debit]]-Table3[[#This Row],[Adjustments_Credit]],"0"))=0,"",(ABS(IF(Table3[[#This Row],[Unadjusted_Debit]]>=0,Table3[[#This Row],[Unadjusted_Debit]]+Table3[[#This Row],[Adjustments_Debit]]-Table3[[#This Row],[Adjustments_Credit]],"0")))) -> 7300 | I43: NO | J43: =IF(Table3[[#This Row],[HST_Eligible]]="YES",Table3[[#This Row],[Adjusted_Debit]]*0.13,IF(Table3[[#This Row],[Adjusted_Debit]]="Partial",Table3[[#Headers],[Adjusted_Debit]]*0.13*0.5,IF(Table3[[#This Row],[HST_Eligible]]="NO",0,""))) -> 0
A44: 5130 | B44: WSIB Premiums | C44: 5273 | G44: =IF(ABS(IF(Table3[[#This Row],[Unadjusted_Debit]]>=0,Table3[[#This Row],[Unadjusted_Debit]]+Table3[[#This Row],[Adjustments_Debit]]-Table3[[#This Row],[Adjustments_Credit]],"0"))=0,"",(ABS(IF(Table3[[#This Row],[Unadjusted_Debit]]>=0,Table3[[#This Row],[Unadjusted_Debit]]+Table3[[#This Row],[Adjustments_Debit]]-Table3[[#This Row],[Adjustments_Credit]],"0")))) -> 5273 | I44: NO | J44: =IF(Table3[[#This Row],[HST_Eligible]]="YES",Table3[[#This Row],[Adjusted_Debit]]*0.13,IF(Table3[[#This Row],[Adjusted_Debit]]="Partial",Table3[[#Headers],[Adjusted_Debit]]*0.13*0.5,IF(Table3[[#This Row],[HST_Eligible]]="NO",0,""))) -> 0
A45: 5135 | B45: EHT (Employer Health Tax) | C45: 3932 | G45: =IF(ABS(IF(Table3[[#This Row],[Unadjusted_Debit]]>=0,Table3[[#This Row],[Unadjusted_Debit]]+Table3[[#This Row],[Adjustments_Debit]]-Table3[[#This Row],[Adjustments_Credit]],"0"))=0,"",(ABS(IF(Table3[[#This Row],[Unadjusted_Debit]]>=0,Table3[[#This Row],[Unadjusted_Debit]]+Table3[[#This Row],[Adjustments_Debit]]-Table3[[#This Row],[Adjustments_Credit]],"0")))) -> 3932 | I45: NO | J45: =IF(Table3[[#This Row],[HST_Eligible]]="YES",Table3[[#This Row],[Adjusted_Debit]]*0.13,IF(Table3[[#This Row],[Adjusted_Debit]]="Partial",Table3[[#Headers],[Adjusted_Debit]]*0.13*0.5,IF(Table3[[#This Row],[HST_Eligible]]="NO",0,""))) -> 0
G46: =IF(ABS(IF(Table3[[#This Row],[Unadjusted_Debit]]>=0,Table3[[#This Row],[Unadjusted_Debit]]+Table3[[#This Row],[Adjustments_Debit]]-Table3[[#This Row],[Adjustments_Credit]],"0"))=0,"",(ABS(IF(Table3[[#This Row],[Unadjusted_Debit]]>=0,Table3[[#This Row],[Unadjusted_Debit]]+Table3[[#This Row],[Adjustments_Debit]]-Table3[[#This Row],[Adjustments_Credit]],"0")))) | J46: =IF(Table3[[#This Row],[HST_Eligible]]="YES",Table3[[#This Row],[Adjusted_Debit]]*0.13,IF(Table3[[#This Row],[Adjusted_Debit]]="Partial",Table3[[#Headers],[Adjusted_Debit]]*0.13*0.5,IF(Table3[[#This Row],[HST_Eligible]]="NO",0,"")))
A47: OCCUPANCY COSTS | G47: =IF(ABS(IF(Table3[[#This Row],[Unadjusted_Debit]]>=0,Table3[[#This Row],[Unadjusted_Debit]]+Table3[[#This Row],[Adjustments_Debit]]-Table3[[#This Row],[Adjustments_Credit]],"0"))=0,"",(ABS(IF(Table3[[#This Row],[Unadjusted_Debit]]>=0,Table3[[#This Row],[Unadjusted_Debit]]+Table3[[#This Row],[Adjustments_Debit]]-Table3[[#This Row],[Adjustments_Credit]],"0")))) | J47: =IF(Table3[[#This Row],[HST_Eligible]]="YES",Table3[[#This Row],[Adjusted_Debit]]*0.13,IF(Table3[[#This Row],[Adjusted_Debit]]="Partial",Table3[[#Headers],[Adjusted_Debit]]*0.13*0.5,IF(Table3[[#This Row],[HST_Eligible]]="NO",0,"")))
A48: 5200 | B48: Rent - Building | C48: 45000 | G48: =IF(ABS(IF(Table3[[#This Row],[Unadjusted_Debit]]>=0,Table3[[#This Row],[Unadjusted_Debit]]+Table3[[#This Row],[Adjustments_Debit]]-Table3[[#This Row],[Adjustments_Credit]],"0"))=0,"",(ABS(IF(Table3[[#This Row],[Unadjusted_Debit]]>=0,Table3[[#This Row],[Unadjusted_Debit]]+Table3[[#This Row],[Adjustments_Debit]]-Table3[[#This Row],[Adjustments_Credit]],"0")))) -> 45000 | I48: YES | J48: =IF(Table3[[#This Row],[HST_Eligible]]="YES",Table3[[#This Row],[Adjusted_Debit]]*0.13,IF(Table3[[#This Row],[Adjusted_Debit]]="Partial",Table3[[#Headers],[Adjusted_Debit]]*0.13*0.5,IF(Table3[[#This Row],[HST_Eligible]]="NO",0,""))) -> 5850
A49: 5205 | B49: Property Taxes | C49: 9000 | G49: =IF(ABS(IF(Table3[[#This Row],[Unadjusted_Debit]]>=0,Table3[[#This Row],[Unadjusted_Debit]]+Table3[[#This Row],[Adjustments_Debit]]-Table3[[#This Row],[Adjustments_Credit]],"0"))=0,"",(ABS(IF(Table3[[#This Row],[Unadjusted_Debit]]>=0,Table3[[#This Row],[Unadjusted_Debit]]+Table3[[#This Row],[Adjustments_Debit]]-Table3[[#This Row],[Adjustments_Credit]],"0")))) -> 9000 | I49: YES | J49: =IF(Table3[[#This Row],[HST_Eligible]]="YES",Table3[[#This Row],[Adjusted_Debit]]*0.13,IF(Table3[[#This Row],[Adjusted_Debit]]="Partial",Table3[[#Headers],[Adjusted_Debit]]*0.13*0.5,IF(Table3[[#This Row],[HST_Eligible]]="NO",0,""))) -> 1170
A50: 5210 | B50: Utilities - Electricity | C50: 6200 | G50: =IF(ABS(IF(Table3[[#This Row],[Unadjusted_Debit]]>=0,Table3[[#This Row],[Unadjusted_Debit]]+Table3[[#This Row],[Adjustments_Debit]]-Table3[[#This Row],[Adjustments_Credit]],"0"))=0,"",(ABS(IF(Table3[[#This Row],[Unadjusted_Debit]]>=0,Table3[[#This Row],[Unadjusted_Debit]]+Table3[[#This Row],[Adjustments_Debit]]-Table3[[#This Row],[Adjustments_Credit]],"0")))) -> 6200 | I50: YES | J50: =IF(Table3[[#This Row],[HST_Eligible]]="YES",Table3[[#This Row],[Adjusted_Debit]]*0.13,IF(Table3[[#This Row],[Adjusted_Debit]]="Partial",Table3[[#Headers],[Adjusted_Debit]]*0.13*0.5,IF(Table3[[#This Row],[HST_Eligible]]="NO",0,""))) -> 806
A51: 5215 | B51: Utilities - Gas/Heating | C51: 2800 | G51: =IF(ABS(IF(Table3[[#This Row],[Unadjusted_Debit]]>=0,Table3[[#This Row],[Unadjusted_Debit]]+Table3[[#This Row],[Adjustments_Debit]]-Table3[[#This Row],[Adjustments_Credit]],"0"))=0,"",(ABS(IF(Table3[[#This Row],[Unadjusted_Debit]]>=0,Table3[[#This Row],[Unadjusted_Debit]]+Table3[[#This Row],[Adjustments_Debit]]-Table3[[#This Row],[Adjustments_Credit]],"0")))) -> 2800 | I51: YES | J51: =IF(Table3[[#This Row],[HST_Eligible]]="YES",Table3[[#This Row],[Adjusted_Debit]]*0.13,IF(Table3[[#This Row],[Adjusted_Debit]]="Partial",Table3[[#Headers],[Adjusted_Debit]]*0.13*0.5,IF(Table3[[#This Row],[HST_Eligible]]="NO",0,""))) -> 364
A52: 5220 | B52: Utilities - Water & Sewer | C52: 1500 | G52: =IF(ABS(IF(Table3[[#This Row],[Unadjusted_Debit]]>=0,Table3[[#This Row],[Unadjusted_Debit]]+Table3[[#This Row],[Adjustments_Debit]]-Table3[[#This Row],[Adjustments_Credit]],"0"))=0,"",(ABS(IF(Table3[[#This Row],[Unadjusted_Debit]]>=0,Table3[[#This Row],[Unadjusted_Debit]]+Table3[[#This Row],[Adjustments_Debit]]-Table3[[#This Row],[Adjustments_Credit]],"0")))) -> 1500 | I52: YES | J52: =IF(Table3[[#This Row],[HST_Eligible]]="YES",Table3[[#This Row],[Adjusted_Debit]]*0.13,IF(Table3[[#This Row],[Adjusted_Debit]]="Partial",Table3[[#Headers],[Adjusted_Debit]]*0.13*0.5,IF(Table3[[#This Row],[HST_Eligible]]="NO",0,""))) -> 195
A53: 5225 | B53: Property Insurance | C53: 4800 | F53: 600 | G53: =IF(ABS(IF(Table3[[#This Row],[Unadjusted_Debit]]>=0,Table3[[#This Row],[Unadjusted_Debit]]+Table3[[#This Row],[Adjustments_Debit]]-Table3[[#This Row],[Adjustments_Credit]],"0"))=0,"",(ABS(IF(Table3[[#This Row],[Unadjusted_Debit]]>=0,Table3[[#This Row],[Unadjusted_Debit]]+Table3[[#This Row],[Adjustments_Debit]]-Table3[[#This Row],[Adjustments_Credit]],"0")))) -> 4200 | I53: NO | J53: =IF(Table3[[#This Row],[HST_Eligible]]="YES",Table3[[#This Row],[Adjusted_Debit]]*0.13,IF(Table3[[#This Row],[Adjusted_Debit]]="Partial",Table3[[#Headers],[Adjusted_Debit]]*0.13*0.5,IF(Table3[[#This Row],[HST_Eligible]]="NO",0,""))) -> 0
A54: 5230 | B54: Building Repairs & Maintenance | C54: 6200 | G54: =IF(ABS(IF(Table3[[#This Row],[Unadjusted_Debit]]>=0,Table3[[#This Row],[Unadjusted_Debit]]+Table3[[#This Row],[Adjustments_Debit]]-Table3[[#This Row],[Adjustments_Credit]],"0"))=0,"",(ABS(IF(Table3[[#This Row],[Unadjusted_Debit]]>=0,Table3[[#This Row],[Unadjusted_Debit]]+Table3[[#This Row],[Adjustments_Debit]]-Table3[[#This Row],[Adjustments_Credit]],"0")))) -> 6200 | I54: YES | J54: =IF(Table3[[#This Row],[HST_Eligible]]="YES",Table3[[#This Row],[Adjusted_Debit]]*0.13,IF(Table3[[#This Row],[Adjusted_Debit]]="Partial",Table3[[#Headers],[Adjusted_Debit]]*0.13*0.5,IF(Table3[[#This Row],[HST_Eligible]]="NO",0,""))) -> 806
A55: 5235 | B55: Janitorial & Cleaning Services | C55: 3600 | G55: =IF(ABS(IF(Table3[[#This Row],[Unadjusted_Debit]]>=0,Table3[[#This Row],[Unadjusted_Debit]]+Table3[[#This Row],[Adjustments_Debit]]-Table3[[#This Row],[Adjustments_Credit]],"0"))=0,"",(ABS(IF(Table3[[#This Row],[Unadjusted_Debit]]>=0,Table3[[#This Row],[Unadjusted_Debit]]+Table3[[#This Row],[Adjustments_Debit]]-Table3[[#This Row],[Adjustments_Credit]],"0")))) -> 3600 | I55: YES | J55: =IF(Table3[[#This Row],[HST_Eligible]]="YES",Table3[[#This Row],[Adjusted_Debit]]*0.13,IF(Table3[[#This Row],[Adjusted_Debit]]="Partial",Table3[[#Headers],[Adjusted_Debit]]*0.13*0.5,IF(Table3[[#This Row],[HST_Eligible]]="NO",0,""))) -> 468
A56: 5240 | B56: Security Services | C56: 2400 | G56: =IF(ABS(IF(Table3[[#This Row],[Unadjusted_Debit]]>=0,Table3[[#This Row],[Unadjusted_Debit]]+Table3[[#This Row],[Adjustments_Debit]]-Table3[[#This Row],[Adjustments_Credit]],"0"))=0,"",(ABS(IF(Table3[[#This Row],[Unadjusted_Debit]]>=0,Table3[[#This Row],[Unadjusted_Debit]]+Table3[[#This Row],[Adjustments_Debit]]-Table3[[#This Row],[Adjustments_Credit]],"0")))) -> 2400 | I56: YES | J56: =IF(Table3[[#This Row],[HST_Eligible]]="YES",Table3[[#This Row],[Adjusted_Debit]]*0.13,IF(Table3[[#This Row],[Adjusted_Debit]]="Partial",Table3[[#Headers],[Adjusted_Debit]]*0.13*0.5,IF(Table3[[#This Row],[HST_Eligible]]="NO",0,""))) -> 312
A57: 5245 | B57: Waste Removal & Recycling | C57: 1200 | G57: =IF(ABS(IF(Table3[[#This Row],[Unadjusted_Debit]]>=0,Table3[[#This Row],[Unadjusted_Debit]]+Table3[[#This Row],[Adjustments_Debit]]-Table3[[#This Row],[Adjustments_Credit]],"0"))=0,"",(ABS(IF(Table3[[#This Row],[Unadjusted_Debit]]>=0,Table3[[#This Row],[Unadjusted_Debit]]+Table3[[#This Row],[Adjustments_Debit]]-Table3[[#This Row],[Adjustments_Credit]],"0")))) -> 1200 | I57: YES | J57: =IF(Table3[[#This Row],[HST_Eligible]]="YES",Table3[[#This Row],[Adjusted_Debit]]*0.13,IF(Table3[[#This Row],[Adjusted_Debit]]="Partial",Table3[[#Headers],[Adjusted_Debit]]*0.13*0.5,IF(Table3[[#This Row],[HST_Eligible]]="NO",0,""))) -> 156
G58: =IF(ABS(IF(Table3[[#This Row],[Unadjusted_Debit]]>=0,Table3[[#This Row],[Unadjusted_Debit]]+Table3[[#This Row],[Adjustments_Debit]]-Table3[[#This Row],[Adjustments_Credit]],"0"))=0,"",(ABS(IF(Table3[[#This Row],[Unadjusted_Debit]]>=0,Table3[[#This Row],[Unadjusted_Debit]]+Table3[[#This Row],[Adjustments_Debit]]-Table3[[#This Row],[Adjustments_Credit]],"0")))) | J58: =IF(Table3[[#This Row],[HST_Eligible]]="YES",Table3[[#This Row],[Adjusted_Debit]]*0.13,IF(Table3[[#This Row],[Adjusted_Debit]]="Partial",Table3[[#Headers],[Adjusted_Debit]]*0.13*0.5,IF(Table3[[#This Row],[HST_Eligible]]="NO",0,"")))
A59: VEHICLE & EQUIPMENT | G59: =IF(ABS(IF(Table3[[#This Row],[Unadjusted_Debit]]>=0,Table3[[#This Row],[Unadjusted_Debit]]+Table3[[#This Row],[Adjustments_Debit]]-Table3[[#This Row],[Adjustments_Credit]],"0"))=0,"",(ABS(IF(Table3[[#This Row],[Unadjusted_Debit]]>=0,Table3[[#This Row],[Unadjusted_Debit]]+Table3[[#This Row],[Adjustments_Debit]]-Table3[[#This Row],[Adjustments_Credit]],"0")))) | J59: =IF(Table3[[#This Row],[HST_Eligible]]="YES",Table3[[#This Row],[Adjusted_Debit]]*0.13,IF(Table3[[#This Row],[Adjusted_Debit]]="Partial",Table3[[#Headers],[Adjusted_Debit]]*0.13*0.5,IF(Table3[[#This Row],[HST_Eligible]]="NO",0,"")))
A60: 5300 | B60: Fuel - Company Vehicles | C60: 5800 | G60: =IF(ABS(IF(Table3[[#This Row],[Unadjusted_Debit]]>=0,Table3[[#This Row],[Unadjusted_Debit]]+Table3[[#This Row],[Adjustments_Debit]]-Table3[[#This Row],[Adjustments_Credit]],"0"))=0,"",(ABS(IF(Table3[[#This Row],[Unadjusted_Debit]]>=0,Table3[[#This Row],[Unadjusted_Debit]]+Table3[[#This Row],[Adjustments_Debit]]-Table3[[#This Row],[Adjustments_Credit]],"0")))) -> 5800 | I60: YES | J60: =IF(Table3[[#This Row],[HST_Eligible]]="YES",Table3[[#This Row],[Adjusted_Debit]]*0.13,IF(Table3[[#This Row],[Adjusted_Debit]]="Partial",Table3[[#Headers],[Adjusted_Debit]]*0.13*0.5,IF(Table3[[#This Row],[HST_Eligible]]="NO",0,""))) -> 754
A61: 5305 | B61: Fuel - Demo Vehicles | C61: 3000 | G61: =IF(ABS(IF(Table3[[#This Row],[Unadjusted_Debit]]>=0,Table3[[#This Row],[Unadjusted_Debit]]+Table3[[#This Row],[Adjustments_Debit]]-Table3[[#This Row],[Adjustments_Credit]],"0"))=0,"",(ABS(IF(Table3[[#This Row],[Unadjusted_Debit]]>=0,Table3[[#This Row],[Unadjusted_Debit]]+Table3[[#This Row],[Adjustments_Debit]]-Table3[[#This Row],[Adjustments_Credit]],"0")))) -> 3000 | I61: YES | J61: =IF(Table3[[#This Row],[HST_Eligible]]="YES",Table3[[#This Row],[Adjusted_Debit]]*0.13,IF(Table3[[#This Row],[Adjusted_Debit]]="Partial",Table3[[#Headers],[Adjusted_Debit]]*0.13*0.5,IF(Table3[[#This Row],[HST_Eligible]]="NO",0,""))) -> 390
A62: 5310 | B62: Vehicle Repairs & Maintenance | C62: 4900 | G62: =IF(ABS(IF(Table3[[#This Row],[Unadjusted_Debit]]>=0,Table3[[#This Row],[Unadjusted_Debit]]+Table3[[#This Row],[Adjustments_Debit]]-Table3[[#This Row],[Adjustments_Credit]],"0"))=0,"",(ABS(IF(Table3[[#This Row],[Unadjusted_Debit]]>=0,Table3[[#This Row],[Unadjusted_Debit]]+Table3[[#This Row],[Adjustments_Debit]]-Table3[[#This Row],[Adjustments_Credit]],"0")))) -> 4900 | I62: YES | J62: =IF(Table3[[#This Row],[HST_Eligible]]="YES",Table3[[#This Row],[Adjusted_Debit]]*0.13,IF(Table3[[#This Row],[Adjusted_Debit]]="Partial",Table3[[#Headers],[Adjusted_Debit]]*0.13*0.5,IF(Table3[[#This Row],[HST_Eligible]]="NO",0,""))) -> 637
A63: 5315 | B63: Vehicle Insurance | C63: 3200 | G63: =IF(ABS(IF(Table3[[#This Row],[Unadjusted_Debit]]>=0,Table3[[#This Row],[Unadjusted_Debit]]+Table3[[#This Row],[Adjustments_Debit]]-Table3[[#This Row],[Adjustments_Credit]],"0"))=0,"",(ABS(IF(Table3[[#This Row],[Unadjusted_Debit]]>=0,Table3[[#This Row],[Unadjusted_Debit]]+Table3[[#This Row],[Adjustments_Debit]]-Table3[[#This Row],[Adjustments_Credit]],"0")))) -> 3200 | I63: NO | J63: =IF(Table3[[#This Row],[HST_Eligible]]="YES",Table3[[#This Row],[Adjusted_Debit]]*0.13,IF(Table3[[#This Row],[Adjusted_Debit]]="Partial",Table3[[#Headers],[Adjusted_Debit]]*0.13*0.5,IF(Table3[[#This Row],[HST_Eligible]]="NO",0,""))) -> 0
A64: 5320 | B64: Vehicle Licenses & Registration | C64: 850 | G64: =IF(ABS(IF(Table3[[#This Row],[Unadjusted_Debit]]>=0,Table3[[#This Row],[Unadjusted_Debit]]+Table3[[#This Row],[Adjustments_Debit]]-Table3[[#This Row],[Adjustments_Credit]],"0"))=0,"",(ABS(IF(Table3[[#This Row],[Unadjusted_Debit]]>=0,Table3[[#This Row],[Unadjusted_Debit]]+Table3[[#This Row],[Adjustments_Debit]]-Table3[[#This Row],[Adjustments_Credit]],"0")))) -> 850 | I64: YES | J64: =IF(Table3[[#This Row],[HST_Eligible]]="YES",Table3[[#This Row],[Adjusted_Debit]]*0.13,IF(Table3[[#This Row],[Adjusted_Debit]]="Partial",Table3[[#Headers],[Adjusted_Debit]]*0.13*0.5,IF(Table3[[#This Row],[HST_Eligible]]="NO",0,""))) -> 110.5
A65: 5325 | B65: Equipment Repairs & Maintenance | C65: 3130 | G65: =IF(ABS(IF(Table3[[#This Row],[Unadjusted_Debit]]>=0,Table3[[#This Row],[Unadjusted_Debit]]+Table3[[#This Row],[Adjustments_Debit]]-Table3[[#This Row],[Adjustments_Credit]],"0"))=0,"",(ABS(IF(Table3[[#This Row],[Unadjusted_Debit]]>=0,Table3[[#This Row],[Unadjusted_Debit]]+Table3[[#This Row],[Adjustments_Debit]]-Table3[[#This Row],[Adjustments_Credit]],"0")))) -> 3130 | I65: YES | J65: =IF(Table3[[#This Row],[HST_Eligible]]="YES",Table3[[#This Row],[Adjusted_Debit]]*0.13,IF(Table3[[#This Row],[Adjusted_Debit]]="Partial",Table3[[#Headers],[Adjusted_Debit]]*0.13*0.5,IF(Table3[[#This Row],[HST_Eligible]]="NO",0,""))) -> 406.9
A66: 5330 | B66: Equipment Rental & Leasing | C66: 2400 | G66: =IF(ABS(IF(Table3[[#This Row],[Unadjusted_Debit]]>=0,Table3[[#This Row],[Unadjusted_Debit]]+Table3[[#This Row],[Adjustments_Debit]]-Table3[[#This Row],[Adjustments_Credit]],"0"))=0,"",(ABS(IF(Table3[[#This Row],[Unadjusted_Debit]]>=0,Table3[[#This Row],[Unadjusted_Debit]]+Table3[[#This Row],[Adjustments_Debit]]-Table3[[#This Row],[Adjustments_Credit]],"0")))) -> 2400 | I66: YES | J66: =IF(Table3[[#This Row],[HST_Eligible]]="YES",Table3[[#This Row],[Adjusted_Debit]]*0.13,IF(Table3[[#This Row],[Adjusted_Debit]]="Partial",Table3[[#Headers],[Adjusted_Debit]]*0.13*0.5,IF(Table3[[#This Row],[HST_Eligible]]="NO",0,""))) -> 312
A67: 5335 | B67: Small Tools & Equipment | C67: 2550 | G67: =IF(ABS(IF(Table3[[#This Row],[Unadjusted_Debit]]>=0,Table3[[#This Row],[Unadjusted_Debit]]+Table3[[#This Row],[Adjustments_Debit]]-Table3[[#This Row],[Adjustments_Credit]],"0"))=0,"",(ABS(IF(Table3[[#This Row],[Unadjusted_Debit]]>=0,Table3[[#This Row],[Unadjusted_Debit]]+Table3[[#This Row],[Adjustments_Debit]]-Table3[[#This Row],[Adjustments_Credit]],"0")))) -> 2550 | I67: YES | J67: =IF(Table3[[#This Row],[HST_Eligible]]="YES",Table3[[#This Row],[Adjusted_Debit]]*0.13,IF(Table3[[#This Row],[Adjusted_Debit]]="Partial",Table3[[#Headers],[Adjusted_Debit]]*0.13*0.5,IF(Table3[[#This Row],[HST_Eligible]]="NO",0,""))) -> 331.5
G68: =IF(ABS(IF(Table3[[#This Row],[Unadjusted_Debit]]>=0,Table3[[#This Row],[Unadjusted_Debit]]+Table3[[#This Row],[Adjustments_Debit]]-Table3[[#This Row],[Adjustments_Credit]],"0"))=0,"",(ABS(IF(Table3[[#This Row],[Unadjusted_Debit]]>=0,Table3[[#This Row],[Unadjusted_Debit]]+Table3[[#This Row],[Adjustments_Debit]]-Table3[[#This Row],[Adjustments_Credit]],"0")))) | J68: =IF(Table3[[#This Row],[HST_Eligible]]="YES",Table3[[#This Row],[Adjusted_Debit]]*0.13,IF(Table3[[#This Row],[Adjusted_Debit]]="Partial",Table3[[#Headers],[Adjusted_Debit]]*0.13*0.5,IF(Table3[[#This Row],[HST_Eligible]]="NO",0,"")))
A69: OFFICE & ADMINISTRATIVE | G69: =IF(ABS(IF(Table3[[#This Row],[Unadjusted_Debit]]>=0,Table3[[#This Row],[Unadjusted_Debit]]+Table3[[#This Row],[Adjustments_Debit]]-Table3[[#This Row],[Adjustments_Credit]],"0"))=0,"",(ABS(IF(Table3[[#This Row],[Unadjusted_Debit]]>=0,Table3[[#This Row],[Unadjusted_Debit]]+Table3[[#This Row],[Adjustments_Debit]]-Table3[[#This Row],[Adjustments_Credit]],"0")))) | J69: =IF(Table3[[#This Row],[HST_Eligible]]="YES",Table3[[#This Row],[Adjusted_Debit]]*0.13,IF(Table3[[#This Row],[Adjusted_Debit]]="Partial",Table3[[#Headers],[Adjusted_Debit]]*0.13*0.5,IF(Table3[[#This Row],[HST_Eligible]]="NO",0,"")))
A70: 5400 | B70: Office Supplies & Stationery | C70: 3650 | G70: =IF(ABS(IF(Table3[[#This Row],[Unadjusted_Debit]]>=0,Table3[[#This Row],[Unadjusted_Debit]]+Table3[[#This Row],[Adjustments_Debit]]-Table3[[#This Row],[Adjustments_Credit]],"0"))=0,"",(ABS(IF(Table3[[#This Row],[Unadjusted_Debit]]>=0,Table3[[#This Row],[Unadjusted_Debit]]+Table3[[#This Row],[Adjustments_Debit]]-Table3[[#This Row],[Adjustments_Credit]],"0")))) -> 3650 | I70: YES | J70: =IF(Table3[[#This Row],[HST_Eligible]]="YES",Table3[[#This Row],[Adjusted_Debit]]*0.13,IF(Table3[[#This Row],[Adjusted_Debit]]="Partial",Table3[[#Headers],[Adjusted_Debit]]*0.13*0.5,IF(Table3[[#This Row],[HST_Eligible]]="NO",0,""))) -> 474.5
A71: 5405 | B71: Postage & Courier Services | C71: 1200 | G71: =IF(ABS(IF(Table3[[#This Row],[Unadjusted_Debit]]>=0,Table3[[#This Row],[Unadjusted_Debit]]+Table3[[#This Row],[Adjustments_Debit]]-Table3[[#This Row],[Adjustments_Credit]],"0"))=0,"",(ABS(IF(Table3[[#This Row],[Unadjusted_Debit]]>=0,Table3[[#This Row],[Unadjusted_Debit]]+Table3[[#This Row],[Adjustments_Debit]]-Table3[[#This Row],[Adjustments_Credit]],"0")))) -> 1200 | I71: YES | J71: =IF(Table3[[#This Row],[HST_Eligible]]="YES",Table3[[#This Row],[Adjusted_Debit]]*0.13,IF(Table3[[#This Row],[Adjusted_Debit]]="Partial",Table3[[#Headers],[Adjusted_Debit]]*0.13*0.5,IF(Table3[[#This Row],[HST_Eligible]]="NO",0,""))) -> 156
A72: 5410 | B72: Computer Equipment & Hardware | C72: 6300 | G72: =IF(ABS(IF(Table3[[#This Row],[Unadjusted_Debit]]>=0,Table3[[#This Row],[Unadjusted_Debit]]+Table3[[#This Row],[Adjustments_Debit]]-Table3[[#This Row],[Adjustments_Credit]],"0"))=0,"",(ABS(IF(Table3[[#This Row],[Unadjusted_Debit]]>=0,Table3[[#This Row],[Unadjusted_Debit]]+Table3[[#This Row],[Adjustments_Debit]]-Table3[[#This Row],[Adjustments_Credit]],"0")))) -> 6300 | I72: YES | J72: =IF(Table3[[#This Row],[HST_Eligible]]="YES",Table3[[#This Row],[Adjusted_Debit]]*0.13,IF(Table3[[#This Row],[Adjusted_Debit]]="Partial",Table3[[#Headers],[Adjusted_Debit]]*0.13*0.5,IF(Table3[[#This Row],[HST_Eligible]]="NO",0,""))) -> 819
A73: 5415 | B73: Computer Software & Licenses | C73: 2550 | G73: =IF(ABS(IF(Table3[[#This Row],[Unadjusted_Debit]]>=0,Table3[[#This Row],[Unadjusted_Debit]]+Table3[[#This Row],[Adjustments_Debit]]-Table3[[#This Row],[Adjustments_Credit]],"0"))=0,"",(ABS(IF(Table3[[#This Row],[Unadjusted_Debit]]>=0,Table3[[#This Row],[Unadjusted_Debit]]+Table3[[#This Row],[Adjustments_Debit]]-Table3[[#This Row],[Adjustments_Credit]],"0")))) -> 2550 | I73: YES | J73: =IF(Table3[[#This Row],[HST_Eligible]]="YES",Table3[[#This Row],[Adjusted_Debit]]*0.13,IF(Table3[[#This Row],[Adjusted_Debit]]="Partial",Table3[[#Headers],[Adjusted_Debit]]*0.13*0.5,IF(Table3[[#This Row],[HST_Eligible]]="NO",0,""))) -> 331.5
A74: 5420 | B74: Telephone & Internet | C74: 5400 | G74: =IF(ABS(IF(Table3[[#This Row],[Unadjusted_Debit]]>=0,Table3[[#This Row],[Unadjusted_Debit]]+Table3[[#This Row],[Adjustments_Debit]]-Table3[[#This Row],[Adjustments_Credit]],"0"))=0,"",(ABS(IF(Table3[[#This Row],[Unadjusted_Debit]]>=0,Table3[[#This Row],[Unadjusted_Debit]]+Table3[[#This Row],[Adjustments_Debit]]-Table3[[#This Row],[Adjustments_Credit]],"0")))) -> 5400 | I74: YES | J74: =IF(Table3[[#This Row],[HST_Eligible]]="YES",Table3[[#This Row],[Adjusted_Debit]]*0.13,IF(Table3[[#This Row],[Adjusted_Debit]]="Partial",Table3[[#Headers],[Adjusted_Debit]]*0.13*0.5,IF(Table3[[#This Row],[HST_Eligible]]="NO",0,""))) -> 702
A75: 5425 | B75: Printing & Copying | C75: 2050 | G75: =IF(ABS(IF(Table3[[#This Row],[Unadjusted_Debit]]>=0,Table3[[#This Row],[Unadjusted_Debit]]+Table3[[#This Row],[Adjustments_Debit]]-Table3[[#This Row],[Adjustments_Credit]],"0"))=0,"",(ABS(IF(Table3[[#This Row],[Unadjusted_Debit]]>=0,Table3[[#This Row],[Unadjusted_Debit]]+Table3[[#This Row],[Adjustments_Debit]]-Table3[[#This Row],[Adjustments_Credit]],"0")))) -> 2050 | I75: YES | J75: =IF(Table3[[#This Row],[HST_Eligible]]="YES",Table3[[#This Row],[Adjusted_Debit]]*0.13,IF(Table3[[#This Row],[Adjusted_Debit]]="Partial",Table3[[#Headers],[Adjusted_Debit]]*0.13*0.5,IF(Table3[[#This Row],[HST_Eligible]]="NO",0,""))) -> 266.5
A76: 5430 | B76: Subscriptions & Publications | C76: 960 | G76: =IF(ABS(IF(Table3[[#This Row],[Unadjusted_Debit]]>=0,Table3[[#This Row],[Unadjusted_Debit]]+Table3[[#This Row],[Adjustments_Debit]]-Table3[[#This Row],[Adjustments_Credit]],"0"))=0,"",(ABS(IF(Table3[[#This Row],[Unadjusted_Debit]]>=0,Table3[[#This Row],[Unadjusted_Debit]]+Table3[[#This Row],[Adjustments_Debit]]-Table3[[#This Row],[Adjustments_Credit]],"0")))) -> 960 | I76: YES | J76: =IF(Table3[[#This Row],[HST_Eligible]]="YES",Table3[[#This Row],[Adjusted_Debit]]*0.13,IF(Table3[[#This Row],[Adjusted_Debit]]="Partial",Table3[[#Headers],[Adjusted_Debit]]*0.13*0.5,IF(Table3[[#This Row],[HST_Eligible]]="NO",0,""))) -> 124.8
G77: =IF(ABS(IF(Table3[[#This Row],[Unadjusted_Debit]]>=0,Table3[[#This Row],[Unadjusted_Debit]]+Table3[[#This Row],[Adjustments_Debit]]-Table3[[#This Row],[Adjustments_Credit]],"0"))=0,"",(ABS(IF(Table3[[#This Row],[Unadjusted_Debit]]>=0,Table3[[#This Row],[Unadjusted_Debit]]+Table3[[#This Row],[Adjustments_Debit]]-Table3[[#This Row],[Adjustments_Credit]],"0")))) | J77: =IF(Table3[[#This Row],[HST_Eligible]]="YES",Table3[[#This Row],[Adjusted_Debit]]*0.13,IF(Table3[[#This Row],[Adjusted_Debit]]="Partial",Table3[[#Headers],[Adjusted_Debit]]*0.13*0.5,IF(Table3[[#This Row],[HST_Eligible]]="NO",0,"")))
A78: PROFESSIONAL SERVICES | G78: =IF(ABS(IF(Table3[[#This Row],[Unadjusted_Debit]]>=0,Table3[[#This Row],[Unadjusted_Debit]]+Table3[[#This Row],[Adjustments_Debit]]-Table3[[#This Row],[Adjustments_Credit]],"0"))=0,"",(ABS(IF(Table3[[#This Row],[Unadjusted_Debit]]>=0,Table3[[#This Row],[Unadjusted_Debit]]+Table3[[#This Row],[Adjustments_Debit]]-Table3[[#This Row],[Adjustments_Credit]],"0")))) | J78: =IF(Table3[[#This Row],[HST_Eligible]]="YES",Table3[[#This Row],[Adjusted_Debit]]*0.13,IF(Table3[[#This Row],[Adjusted_Debit]]="Partial",Table3[[#Headers],[Adjusted_Debit]]*0.13*0.5,IF(Table3[[#This Row],[HST_Eligible]]="NO",0,"")))
A79: 5600 | B79: Legal Fees | C79: 4000 | G79: =IF(ABS(IF(Table3[[#This Row],[Unadjusted_Debit]]>=0,Table3[[#This Row],[Unadjusted_Debit]]+Table3[[#This Row],[Adjustments_Debit]]-Table3[[#This Row],[Adjustments_Credit]],"0"))=0,"",(ABS(IF(Table3[[#This Row],[Unadjusted_Debit]]>=0,Table3[[#This Row],[Unadjusted_Debit]]+Table3[[#This Row],[Adjustments_Debit]]-Table3[[#This Row],[Adjustments_Credit]],"0")))) -> 4000 | I79: YES | J79: =IF(Table3[[#This Row],[HST_Eligible]]="YES",Table3[[#This Row],[Adjusted_Debit]]*0.13,IF(Table3[[#This Row],[Adjusted_Debit]]="Partial",Table3[[#Headers],[Adjusted_Debit]]*0.13*0.5,IF(Table3[[#This Row],[HST_Eligible]]="NO",0,""))) -> 520
A80: 5605 | B80: Accounting & Bookkeeping | C80: 7500 | G80: =IF(ABS(IF(Table3[[#This Row],[Unadjusted_Debit]]>=0,Table3[[#This Row],[Unadjusted_Debit]]+Table3[[#This Row],[Adjustments_Debit]]-Table3[[#This Row],[Adjustments_Credit]],"0"))=0,"",(ABS(IF(Table3[[#This Row],[Unadjusted_Debit]]>=0,Table3[[#This Row],[Unadjusted_Debit]]+Table3[[#This Row],[Adjustments_Debit]]-Table3[[#This Row],[Adjustments_Credit]],"0")))) -> 7500 | I80: YES | J80: =IF(Table3[[#This Row],[HST_Eligible]]="YES",Table3[[#This Row],[Adjusted_Debit]]*0.13,IF(Table3[[#This Row],[Adjusted_Debit]]="Partial",Table3[[#Headers],[Adjusted_Debit]]*0.13*0.5,IF(Table3[[#This Row],[HST_Eligible]]="NO",0,""))) -> 975
A81: 5610 | B81: Consulting Fees | C81: 3500 | G81: =IF(ABS(IF(Table3[[#This Row],[Unadjusted_Debit]]>=0,Table3[[#This Row],[Unadjusted_Debit]]+Table3[[#This Row],[Adjustments_Debit]]-Table3[[#This Row],[Adjustments_Credit]],"0"))=0,"",(ABS(IF(Table3[[#This Row],[Unadjusted_Debit]]>=0,Table3[[#This Row],[Unadjusted_Debit]]+Table3[[#This Row],[Adjustments_Debit]]-Table3[[#This Row],[Adjustments_Credit]],"0")))) -> 3500 | I81: YES | J81: =IF(Table3[[#This Row],[HST_Eligible]]="YES",Table3[[#This Row],[Adjusted_Debit]]*0.13,IF(Table3[[#This Row],[Adjusted_Debit]]="Partial",Table3[[#Headers],[Adjusted_Debit]]*0.13*0.5,IF(Table3[[#This Row],[HST_Eligible]]="NO",0,""))) -> 455
A82: 5615 | B82: IT Services & Technical Support | C82: 2800 | G82: =IF(ABS(IF(Table3[[#This Row],[Unadjusted_Debit]]>=0,Table3[[#This Row],[Unadjusted_Debit]]+Table3[[#This Row],[Adjustments_Debit]]-Table3[[#This Row],[Adjustments_Credit]],"0"))=0,"",(ABS(IF(Table3[[#This Row],[Unadjusted_Debit]]>=0,Table3[[#This Row],[Unadjusted_Debit]]+Table3[[#This Row],[Adjustments_Debit]]-Table3[[#This Row],[Adjustments_Credit]],"0")))) -> 2800 | I82: YES | J82: =IF(Table3[[#This Row],[HST_Eligible]]="YES",Table3[[#This Row],[Adjusted_Debit]]*0.13,IF(Table3[[#This Row],[Adjusted_Debit]]="Partial",Table3[[#Headers],[Adjusted_Debit]]*0.13*0.5,IF(Table3[[#This Row],[HST_Eligible]]="NO",0,""))) -> 364
A83: 5620 | B83: Payroll Processing Services | C83: 1800 | G83: =IF(ABS(IF(Table3[[#This Row],[Unadjusted_Debit]]>=0,Table3[[#This Row],[Unadjusted_Debit]]+Table3[[#This Row],[Adjustments_Debit]]-Table3[[#This Row],[Adjustments_Credit]],"0"))=0,"",(ABS(IF(Table3[[#This Row],[Unadjusted_Debit]]>=0,Table3[[#This Row],[Unadjusted_Debit]]+Table3[[#This Row],[Adjustments_Debit]]-Table3[[#This Row],[Adjustments_Credit]],"0")))) -> 1800 | I83: YES | J83: =IF(Table3[[#This Row],[HST_Eligible]]="YES",Table3[[#This Row],[Adjusted_Debit]]*0.13,IF(Table3[[#This Row],[Adjusted_Debit]]="Partial",Table3[[#Headers],[Adjusted_Debit]]*0.13*0.5,IF(Table3[[#This Row],[HST_Eligible]]="NO",0,""))) -> 234
G84: =IF(ABS(IF(Table3[[#This Row],[Unadjusted_Debit]]>=0,Table3[[#This Row],[Unadjusted_Debit]]+Table3[[#This Row],[Adjustments_Debit]]-Table3[[#This Row],[Adjustments_Credit]],"0"))=0,"",(ABS(IF(Table3[[#This Row],[Unadjusted_Debit]]>=0,Table3[[#This Row],[Unadjusted_Debit]]+Table3[[#This Row],[Adjustments_Debit]]-Table3[[#This Row],[Adjustments_Credit]],"0")))) | J84: =IF(Table3[[#This Row],[HST_Eligible]]="YES",Table3[[#This Row],[Adjusted_Debit]]*0.13,IF(Table3[[#This Row],[Adjusted_Debit]]="Partial",Table3[[#Headers],[Adjusted_Debit]]*0.13*0.5,IF(Table3[[#This Row],[HST_Eligible]]="NO",0,"")))
A85: MARKETING & ADVERTISING | G85: =IF(ABS(IF(Table3[[#This Row],[Unadjusted_Debit]]>=0,Table3[[#This Row],[Unadjusted_Debit]]+Table3[[#This Row],[Adjustments_Debit]]-Table3[[#This Row],[Adjustments_Credit]],"0"))=0,"",(ABS(IF(Table3[[#This Row],[Unadjusted_Debit]]>=0,Table3[[#This Row],[Unadjusted_Debit]]+Table3[[#This Row],[Adjustments_Debit]]-Table3[[#This Row],[Adjustments_Credit]],"0")))) | J85: =IF(Table3[[#This Row],[HST_Eligible]]="YES",Table3[[#This Row],[Adjusted_Debit]]*0.13,IF(Table3[[#This Row],[Adjusted_Debit]]="Partial",Table3[[#Headers],[Adjusted_Debit]]*0.13*0.5,IF(Table3[[#This Row],[HST_Eligible]]="NO",0,"")))
A86: 5500 | B86: Advertising - Digital (Google/Facebook) | C86: 14500 | G86: =IF(ABS(IF(Table3[[#This Row],[Unadjusted_Debit]]>=0,Table3[[#This Row],[Unadjusted_Debit]]+Table3[[#This Row],[Adjustments_Debit]]-Table3[[#This Row],[Adjustments_Credit]],"0"))=0,"",(ABS(IF(Table3[[#This Row],[Unadjusted_Debit]]>=0,Table3[[#This Row],[Unadjusted_Debit]]+Table3[[#This Row],[Adjustments_Debit]]-Table3[[#This Row],[Adjustments_Credit]],"0")))) -> 14500 | I86: YES | J86: =IF(Table3[[#This Row],[HST_Eligible]]="YES",Table3[[#This Row],[Adjusted_Debit]]*0.13,IF(Table3[[#This Row],[Adjusted_Debit]]="Partial",Table3[[#Headers],[Adjusted_Debit]]*0.13*0.5,IF(Table3[[#This Row],[HST_Eligible]]="NO",0,""))) -> 1885
A87: 5505 | B87: Advertising - Print, Radio & TV | C87: 8900 | G87: =IF(ABS(IF(Table3[[#This Row],[Unadjusted_Debit]]>=0,Table3[[#This Row],[Unadjusted_Debit]]+Table3[[#This Row],[Adjustments_Debit]]-Table3[[#This Row],[Adjustments_Credit]],"0"))=0,"",(ABS(IF(Table3[[#This Row],[Unadjusted_Debit]]>=0,Table3[[#This Row],[Unadjusted_Debit]]+Table3[[#This Row],[Adjustments_Debit]]-Table3[[#This Row],[Adjustments_Credit]],"0")))) -> 8900 | I87: YES | J87: =IF(Table3[[#This Row],[HST_Eligible]]="YES",Table3[[#This Row],[Adjusted_Debit]]*0.13,IF(Table3[[#This Row],[Adjusted_Debit]]="Partial",Table3[[#Headers],[Adjusted_Debit]]*0.13*0.5,IF(Table3[[#This Row],[HST_Eligible]]="NO",0,""))) -> 1157
A88: 5510 | B88: Website Hosting & Maintenance | C88: 1350 | G88: =IF(ABS(IF(Table3[[#This Row],[Unadjusted_Debit]]>=0,Table3[[#This Row],[Unadjusted_Debit]]+Table3[[#This Row],[Adjustments_Debit]]-Table3[[#This Row],[Adjustments_Credit]],"0"))=0,"",(ABS(IF(Table3[[#This Row],[Unadjusted_Debit]]>=0,Table3[[#This Row],[Unadjusted_Debit]]+Table3[[#This Row],[Adjustments_Debit]]-Table3[[#This Row],[Adjustments_Credit]],"0")))) -> 1350 | I88: YES | J88: =IF(Table3[[#This Row],[HST_Eligible]]="YES",Table3[[#This Row],[Adjusted_Debit]]*0.13,IF(Table3[[#This Row],[Adjusted_Debit]]="Partial",Table3[[#Headers],[Adjusted_Debit]]*0.13*0.5,IF(Table3[[#This Row],[HST_Eligible]]="NO",0,""))) -> 175.5
A89: 5515 | B89: Promotional Materials & Signage | C89: 3600 | G89: =IF(ABS(IF(Table3[[#This Row],[Unadjusted_Debit]]>=0,Table3[[#This Row],[Unadjusted_Debit]]+Table3[[#This Row],[Adjustments_Debit]]-Table3[[#This Row],[Adjustments_Credit]],"0"))=0,"",(ABS(IF(Table3[[#This Row],[Unadjusted_Debit]]>=0,Table3[[#This Row],[Unadjusted_Debit]]+Table3[[#This Row],[Adjustments_Debit]]-Table3[[#This Row],[Adjustments_Credit]],"0")))) -> 3600 | I89: YES | J89: =IF(Table3[[#This Row],[HST_Eligible]]="YES",Table3[[#This Row],[Adjusted_Debit]]*0.13,IF(Table3[[#This Row],[Adjusted_Debit]]="Partial",Table3[[#Headers],[Adjusted_Debit]]*0.13*0.5,IF(Table3[[#This Row],[HST_Eligible]]="NO",0,""))) -> 468
A90: 5520 | B90: Trade Shows & Events | C90: 4200 | G90: =IF(ABS(IF(Table3[[#This Row],[Unadjusted_Debit]]>=0,Table3[[#This Row],[Unadjusted_Debit]]+Table3[[#This Row],[Adjustments_Debit]]-Table3[[#This Row],[Adjustments_Credit]],"0"))=0,"",(ABS(IF(Table3[[#This Row],[Unadjusted_Debit]]>=0,Table3[[#This Row],[Unadjusted_Debit]]+Table3[[#This Row],[Adjustments_Debit]]-Table3[[#This Row],[Adjustments_Credit]],"0")))) -> 4200 | I90: YES | J90: =IF(Table3[[#This Row],[HST_Eligible]]="YES",Table3[[#This Row],[Adjusted_Debit]]*0.13,IF(Table3[[#This Row],[Adjusted_Debit]]="Partial",Table3[[#Headers],[Adjusted_Debit]]*0.13*0.5,IF(Table3[[#This Row],[HST_Eligible]]="NO",0,""))) -> 546
A91: 5525 | B91: Photography & Videography | C91: 1800 | G91: =IF(ABS(IF(Table3[[#This Row],[Unadjusted_Debit]]>=0,Table3[[#This Row],[Unadjusted_Debit]]+Table3[[#This Row],[Adjustments_Debit]]-Table3[[#This Row],[Adjustments_Credit]],"0"))=0,"",(ABS(IF(Table3[[#This Row],[Unadjusted_Debit]]>=0,Table3[[#This Row],[Unadjusted_Debit]]+Table3[[#This Row],[Adjustments_Debit]]-Table3[[#This Row],[Adjustments_Credit]],"0")))) -> 1800 | I91: YES | J91: =IF(Table3[[#This Row],[HST_Eligible]]="YES",Table3[[#This Row],[Adjusted_Debit]]*0.13,IF(Table3[[#This Row],[Adjusted_Debit]]="Partial",Table3[[#Headers],[Adjusted_Debit]]*0.13*0.5,IF(Table3[[#This Row],[HST_Eligible]]="NO",0,""))) -> 234
G92: =IF(ABS(IF(Table3[[#This Row],[Unadjusted_Debit]]>=0,Table3[[#This Row],[Unadjusted_Debit]]+Table3[[#This Row],[Adjustments_Debit]]-Table3[[#This Row],[Adjustments_Credit]],"0"))=0,"",(ABS(IF(Table3[[#This Row],[Unadjusted_Debit]]>=0,Table3[[#This Row],[Unadjusted_Debit]]+Table3[[#This Row],[Adjustments_Debit]]-Table3[[#This Row],[Adjustments_Credit]],"0")))) | J92: =IF(Table3[[#This Row],[HST_Eligible]]="YES",Table3[[#This Row],[Adjusted_Debit]]*0.13,IF(Table3[[#This Row],[Adjusted_Debit]]="Partial",Table3[[#Headers],[Adjusted_Debit]]*0.13*0.5,IF(Table3[[#This Row],[HST_Eligible]]="NO",0,"")))
A93: TRAVEL & ENTERTAINMENT | G93: =IF(ABS(IF(Table3[[#This Row],[Unadjusted_Debit]]>=0,Table3[[#This Row],[Unadjusted_Debit]]+Table3[[#This Row],[Adjustments_Debit]]-Table3[[#This Row],[Adjustments_Credit]],"0"))=0,"",(ABS(IF(Table3[[#This Row],[Unadjusted_Debit]]>=0,Table3[[#This Row],[Unadjusted_Debit]]+Table3[[#This Row],[Adjustments_Debit]]-Table3[[#This Row],[Adjustments_Credit]],"0")))) | J93: =IF(Table3[[#This Row],[HST_Eligible]]="YES",Table3[[#This Row],[Adjusted_Debit]]*0.13,IF(Table3[[#This Row],[Adjusted_Debit]]="Partial",Table3[[#Headers],[Adjusted_Debit]]*0.13*0.5,IF(Table3[[#This Row],[HST_Eligible]]="NO",0,"")))
A94: 5800 | B94: Travel - Airfare | C94: 3200 | G94: =IF(ABS(IF(Table3[[#This Row],[Unadjusted_Debit]]>=0,Table3[[#This Row],[Unadjusted_Debit]]+Table3[[#This Row],[Adjustments_Debit]]-Table3[[#This Row],[Adjustments_Credit]],"0"))=0,"",(ABS(IF(Table3[[#This Row],[Unadjusted_Debit]]>=0,Table3[[#This Row],[Unadjusted_Debit]]+Table3[[#This Row],[Adjustments_Debit]]-Table3[[#This Row],[Adjustments_Credit]],"0")))) -> 3200 | I94: YES | J94: =IF(Table3[[#This Row],[HST_Eligible]]="YES",Table3[[#This Row],[Adjusted_Debit]]*0.13,IF(Table3[[#This Row],[Adjusted_Debit]]="Partial",Table3[[#Headers],[Adjusted_Debit]]*0.13*0.5,IF(Table3[[#This Row],[HST_Eligible]]="NO",0,""))) -> 416
A95: 5805 | B95: Travel - Accommodation | C95: 2700 | G95: =IF(ABS(IF(Table3[[#This Row],[Unadjusted_Debit]]>=0,Table3[[#This Row],[Unadjusted_Debit]]+Table3[[#This Row],[Adjustments_Debit]]-Table3[[#This Row],[Adjustments_Credit]],"0"))=0,"",(ABS(IF(Table3[[#This Row],[Unadjusted_Debit]]>=0,Table3[[#This Row],[Unadjusted_Debit]]+Table3[[#This Row],[Adjustments_Debit]]-Table3[[#This Row],[Adjustments_Credit]],"0")))) -> 2700 | I95: YES | J95: =IF(Table3[[#This Row],[HST_Eligible]]="YES",Table3[[#This Row],[Adjusted_Debit]]*0.13,IF(Table3[[#This Row],[Adjusted_Debit]]="Partial",Table3[[#Headers],[Adjusted_Debit]]*0.13*0.5,IF(Table3[[#This Row],[HST_Eligible]]="NO",0,""))) -> 351
A96: 5810 | B96: Meals & Entertainment (50% rule) | C96: 4500 | G96: =IF(ABS(IF(Table3[[#This Row],[Unadjusted_Debit]]>=0,Table3[[#This Row],[Unadjusted_Debit]]+Table3[[#This Row],[Adjustments_Debit]]-Table3[[#This Row],[Adjustments_Credit]],"0"))=0,"",(ABS(IF(Table3[[#This Row],[Unadjusted_Debit]]>=0,Table3[[#This Row],[Unadjusted_Debit]]+Table3[[#This Row],[Adjustments_Debit]]-Table3[[#This Row],[Adjustments_Credit]],"0")))) -> 4500 | I96: PARTIAL | J96: =IF(Table3[[#This Row],[HST_Eligible]]="YES",Table3[[#This Row],[Adjusted_Debit]]*0.13,IF(Table3[[#This Row],[Adjusted_Debit]]="Partial",Table3[[#Headers],[Adjusted_Debit]]*0.13*0.5,IF(Table3[[#This Row],[HST_Eligible]]="NO",0,"")))
A97: 5815 | B97: Vehicle Mileage Reimbursement | C97: 1200 | G97: =IF(ABS(IF(Table3[[#This Row],[Unadjusted_Debit]]>=0,Table3[[#This Row],[Unadjusted_Debit]]+Table3[[#This Row],[Adjustments_Debit]]-Table3[[#This Row],[Adjustments_Credit]],"0"))=0,"",(ABS(IF(Table3[[#This Row],[Unadjusted_Debit]]>=0,Table3[[#This Row],[Unadjusted_Debit]]+Table3[[#This Row],[Adjustments_Debit]]-Table3[[#This Row],[Adjustments_Credit]],"0")))) -> 1200 | I97: YES | J97: =IF(Table3[[#This Row],[HST_Eligible]]="YES",Table3[[#This Row],[Adjusted_Debit]]*0.13,IF(Table3[[#This Row],[Adjusted_Debit]]="Partial",Table3[[#Headers],[Adjusted_Debit]]*0.13*0.5,IF(Table3[[#This Row],[HST_Eligible]]="NO",0,""))) -> 156
A98: 5820 | B98: Conference & Training Registration | C98: 3000 | G98: =IF(ABS(IF(Table3[[#This Row],[Unadjusted_Debit]]>=0,Table3[[#This Row],[Unadjusted_Debit]]+Table3[[#This Row],[Adjustments_Debit]]-Table3[[#This Row],[Adjustments_Credit]],"0"))=0,"",(ABS(IF(Table3[[#This Row],[Unadjusted_Debit]]>=0,Table3[[#This Row],[Unadjusted_Debit]]+Table3[[#This Row],[Adjustments_Debit]]-Table3[[#This Row],[Adjustments_Credit]],"0")))) -> 3000 | I98: YES | J98: =IF(Table3[[#This Row],[HST_Eligible]]="YES",Table3[[#This Row],[Adjusted_Debit]]*0.13,IF(Table3[[#This Row],[Adjusted_Debit]]="Partial",Table3[[#Headers],[Adjusted_Debit]]*0.13*0.5,IF(Table3[[#This Row],[HST_Eligible]]="NO",0,""))) -> 390
A99: 5825 | B99: Professional Memberships & Dues | C99: 680 | G99: =IF(ABS(IF(Table3[[#This Row],[Unadjusted_Debit]]>=0,Table3[[#This Row],[Unadjusted_Debit]]+Table3[[#This Row],[Adjustments_Debit]]-Table3[[#This Row],[Adjustments_Credit]],"0"))=0,"",(ABS(IF(Table3[[#This Row],[Unadjusted_Debit]]>=0,Table3[[#This Row],[Unadjusted_Debit]]+Table3[[#This Row],[Adjustments_Debit]]-Table3[[#This Row],[Adjustments_Credit]],"0")))) -> 680 | I99: YES | J99: =IF(Table3[[#This Row],[HST_Eligible]]="YES",Table3[[#This Row],[Adjusted_Debit]]*0.13,IF(Table3[[#This Row],[Adjusted_Debit]]="Partial",Table3[[#Headers],[Adjusted_Debit]]*0.13*0.5,IF(Table3[[#This Row],[HST_Eligible]]="NO",0,""))) -> 88.4
G100: =IF(ABS(IF(Table3[[#This Row],[Unadjusted_Debit]]>=0,Table3[[#This Row],[Unadjusted_Debit]]+Table3[[#This Row],[Adjustments_Debit]]-Table3[[#This Row],[Adjustments_Credit]],"0"))=0,"",(ABS(IF(Table3[[#This Row],[Unadjusted_Debit]]>=0,Table3[[#This Row],[Unadjusted_Debit]]+Table3[[#This Row],[Adjustments_Debit]]-Table3[[#This Row],[Adjustments_Credit]],"0")))) | J100: =IF(Table3[[#This Row],[HST_Eligible]]="YES",Table3[[#This Row],[Adjusted_Debit]]*0.13,IF(Table3[[#This Row],[Adjusted_Debit]]="Partial",Table3[[#Headers],[Adjusted_Debit]]*0.13*0.5,IF(Table3[[#This Row],[HST_Eligible]]="NO",0,"")))
A101: BANK & FINANCIAL | G101: =IF(ABS(IF(Table3[[#This Row],[Unadjusted_Debit]]>=0,Table3[[#This Row],[Unadjusted_Debit]]+Table3[[#This Row],[Adjustments_Debit]]-Table3[[#This Row],[Adjustments_Credit]],"0"))=0,"",(ABS(IF(Table3[[#This Row],[Unadjusted_Debit]]>=0,Table3[[#This Row],[Unadjusted_Debit]]+Table3[[#This Row],[Adjustments_Debit]]-Table3[[#This Row],[Adjustments_Credit]],"0")))) | J101: =IF(Table3[[#This Row],[HST_Eligible]]="YES",Table3[[#This Row],[Adjusted_Debit]]*0.13,IF(Table3[[#This Row],[Adjusted_Debit]]="Partial",Table3[[#Headers],[Adjusted_Debit]]*0.13*0.5,IF(Table3[[#This Row],[HST_Eligible]]="NO",0,"")))
...

Sheet 11 HST_Return
A1: HST Return - Q4 2024 (October 1 - December 31, 2024)
A3: Line | B3: Description | C3: Amount
A4: 101 | B4: Total Sales (excl. HST) | C4: =SUM('10 Trial Balance '!D26:D29) -> 2218000
A5: 103 | B5: HST Collected (13%) | C5: =C4*0.13 -> 288340
A6: 105 | B6: Adjustments | C6: 0
A7: 106 | B7: Total Purchases (excl. HST) | C7: =SUMIF(Table3[HST_Eligible],"YES",Table3[Adjusted_Debit]) -> 1378740
A8: 108 | B8: Input Tax Credits (ITC) | C8: =C7*0.13 -> 179236.2
A9: 109 | B9: Net HST (Payable)/Refund | C9: =C5-C8 -> 109103.8
A11: HST PAYABLE: | B11: =C9 -> 109103.8 | C11: Amount to remit to CRA
A13: Payment Due Date: | B13: 45688 | C13: Last day of month following quarter

Sheet 12 HST_Rec&JE
A1: HST PAYABLE ACCOUNT RECONCILIATION
A2: Period: Q4 2024 (Oct 1 - Dec 31, 2024)
A3: Discription | B3: Balance | C3: Notes
A4: OPENING BALANCE (from Trial Balance):
A5: Account 2100 - HST Payable | B5: ='10 Trial Balance '!D17 -> 16900 | C5: (Credit balance from previous period)
A7: ACTIVITY THIS QUARTER:
A8: HST Collected on Sales | B8: ='11 HST_Return'!C5 -> 288340 | C8: (Credit - you owe CRA)
A9: Less: Input Tax Credits | B9: ='11 HST_Return'!C8 -> 179236.2 | C9: (Debit - CRA owes you)
A10: Net HST for Quarter | B10: =B8-B9 -> 109103.8
A12: ENDING BALANCE CALCULATION:
A13: Opening Balance | B13: =B5 -> 16900
A14: Plus: Net HST Q4 | B14: =B10 -> 109103.8
A15: TOTAL HST PAYABLE | B15: =SUM(B13:B14) -> 126003.8 | C15: Amount owing to CRA
A17: BREAKDOWN:
A18: Previous period owing | B18: =B13 -> 16900 | C18: (Should have been paid already)
A19: Current period owing | B19: =B14 -> 109103.8 | C19: (Q4 2024)
A20: TOTAL TO REMIT NOW: | B20: =B15 -> 126003.8
A22: Description | B22: Amount
A23: Payment Details:
A24: HST Registration Number: | B24: ASDCCD123E55
A25: Reporting Period: | B25: Q4 2024 (Oct 1 - Dec 31, 2024)
A26: Return Due Date: | B26: 45688
A27: Payment Due Date: | B27: 45688
A29: AMOUNT BREAKDOWN: (From account 2100)
A30: Previous Balance Owing: | B30: =B13 -> 16900
A31: Current Quarter (Q4 2024): | B31: =B19 -> 109103.8
A32: TOTAL AMOUNT TO PAY: | B32: =SUM(B30:B31) -> 126003.8
A34: PAYMENT METHOD:
A35: CRA My Business Account - Online
A36: Pre-authorized Debit
A37: Wire Transfer | B37: ✅
A38: Cheque (mail to CRA)
A40: Payment Confirmation:
A41: Payment Date: | B41: =A52 -> 45688
A42: Confirmation Number:
A43: Amount Paid: | B43: =B32 -> 126003.8
A44: Payment Method: | B44: =A37 -> Wire Transfer
A46: JOURNAL ENTRIES " HST_Q4"
A47: Date | B47: Entry | C47: Account | D47: Account_Name | E47: Debit | F47: Credit | G47: Memo
A48: 45657 | B48: JE-HST-01 | C48: 2100 | D48: HST Payable | E48: 179236.2 | G48: Record Q4 ITCs
A49: 45657 | B49: JE-HST-01 | C49: Various | D49: Expense Accounts | F49: 179236.2 | G49: ITCs on purchases
A50: 45657 | B50: JE-HST-02 | C50: Various | D50: Revenue Accounts | E50: 288340 | G50: Remove HST from revenue
A51: 45657 | B51: JE-HST-02 | C51: 2100 | D51: HST Payable | F51: 288340 | G51: Record Q4 HST collected
A52: 45688 | B52: JE-HST-03 | C52: 2100 | D52: HST Payable | E52: 126003.8 | G52: Payment to CRA Q4 2024
A53: 45688 | B53: JE-HST-03 | C53: 1000 | D53: Cash | F53: 126003.8 | G53: EFT payment to CRA
A55: NET EFFECT ON ACCOUNT 2100 (HST Payable): | B55: Amount
A56: Opening Balance (Credit) | B56: =B5 -> 16900
A57: Plus: HST Collected (Credit) | B57: =B8 -> 288340
A58: Less: ITCs Claimed (Debit) | B58: =B9 -> 179236.2
A59: ENDING BALANCE (Credit) | B59: =B57-B58 -> 109103.8 | C59: ← This is what you owe CRA

Sheet 13 WSIB & EHT
A1: WSIB Annual Premium - 2024
A2: Description | B2: Amount | C2: Calculation / Notes
A3: Total Gross Payroll | B3: ='10 Trial Balance '!G38+'10 Trial Balance '!G39 -> 293400 | C3: =SUM of Salaries & Wages + Overtime (288400 + 5000)
A4: WSIB Rate (per $100 payroll) | B4: 0.85 | C4: 2024 Ontario rate - Automobile & Truck Dealers classification
A5: Annual Premium Due | B5: =B3*B4/100 -> 2493.9 | C5: 293400 * 0.85 / 100
A6: Payment Status | B6: Annual | C6: Report via WSIB online account
A7: Journal Entry - Debit Account | B7: ='10 Trial Balance '!G44 -> 5273 | C7: WSIB Premiums
A8: Journal Entry - Credit Account | B8: ='10 Trial Balance '!H18 -> 21850 | C8: Payroll Liabilities
A9: Due Date | B9: Annual return | C9: Typically with WSIB filing
A11: Employer Health Tax (EHT) - Ontario 2024
A12: Description | B12: Amount | C12: Calculation / Notes
A13: Total Gross Payroll (Ontario) | B13: =B3 -> 293400 | C13: SUM of Salaries & Wages ($288,400) + Overtime ($5,000) from trial balance
A14: EHT Exemption Threshold (2024) | B14: 1000000 | C14: $1,000,000 - permanent since 2020
A15: Taxable Payroll Amount | B15: 0 | C15: =MAX(0, 293400 - 1000000) -> 0
A16: EHT Rate | B16: 0.0195 | C16: Standard rate on taxable payroll
A17: EHT Payable | B17: 0 | C17: =0 * 1.95% -> 0
A18: Associated Employers? | B18: No | C18: Assumed single entity; if group > $5M total payroll → $0 exemption
A19: Eligible for Exemption? | B19: Yes | C19: Payroll < $1M and < $5M group threshold
A20: Filing Required? | B20: Yes | C20: Annual return even if $0
